Workbook

Sheet statadata
A1: code | B1: time | C1: logydsa | D1: loginvdsa | E1: tbysa | F1: logrus | G1: logi
A2: 199 | B2: 19941 | C2: -.01575 | D2: -.1135455 | E2: .0253523 | F2: .007174
A3: 199 | B3: 19942 | C3: -.014127 | D3: -.0959538 | E3: .0171985 | F3: .0192438
A4: 199 | B4: 19943 | C4: -.007504 | D4: -.0533622 | E4: -.0049553 | F4: .0254314
A5: 199 | B5: 19944 | C5: .002119 | D5: -.0277705 | E5: .0098909 | F5: .0320287
A6: 199 | B6: 19951 | C6: .0007419 | D6: -.0231789 | E6: -.0082628 | F6: .040839 | G6: .0643602
A7: 199 | B7: 19952 | C7: -.0036351 | D7: -.0005872 | E7: -.0114166 | F7: .0393857 | G7: .0740769
A8: 199 | B8: 19953 | C8: -.0050121 | D8: -.0129956 | E8: .0014296 | F8: .0355326 | G8: .0598349
A9: 199 | B9: 19954 | C9: -.0073891 | D9: -.010404 | E9: -.0057242 | F9: .038806 | G9: .0593927
A10: 199 | B10: 19961 | C10: .0012339 | D10: .0101877 | E10: .0001221 | F10: .0301179 | G10: .048056
A11: 199 | B11: 19962 | C11: .0118569 | D11: .0307793 | E11: -.0070317 | F11: .0332429 | G11: .048624
A12: 199 | B12: 19963 | C12: .0174798 | D12: .049371 | E12: -.0011855 | F12: .0381779 | G12: .05474
A13: 199 | B13: 19964 | C13: .0211028 | D13: .0609626 | E13: -.0023393 | F13: .0335721 | G13: .0452042
A14: 199 | B14: 19971 | C14: .0187258 | D14: .0695543 | E14: -.010493 | F14: .0328583 | G14: .0432046
A15: 199 | B15: 19972 | C15: .0163488 | D15: .0661459 | E15: -.0046468 | F15: .0369045 | G15: .0448726
A16: 199 | B16: 19973 | C16: .0129718 | D16: .0567375 | E16: -.0048006 | F16: .0350084 | G16: .0429766
A17: 199 | B17: 19974 | C17: .0075948 | D17: .0483292 | E17: -.0049544 | F17: .0349282 | G17: .0428964
... A61: 213 | B61: 20004 | C61: -.0097045 | D61: -.1656921 | E61: .0095148 | F61: .0431779 | G61: .1089656
A62: 213 | B62: 20011 | F62: .0404402
A63: 213 | B63: 20012 | F63: .0221311
A64: 213 | B64: 20013 | F64: .0194032
A65: 213 | B65: 20014 | F65: -.0006314
A66: 223 | B66: 19941 | C66: -.048733 | D66: .0666136 | E66: -.068375 | F66: .007174
A67: 223 | B67: 19942 | C67: -.0382945 | D67: -.0408897 | E67: -.0719778 | F67: .0192438
A68: 223 | B68: 19943 | C68: -.0058561 | D68: -.087393 | E68: .0804194 | F68: .0254314 | G68: .1368833
A69: 223 | B69: 19944 | C69: .0275823 | D69: .1351037 | E69: .0408165 | F69: .0320287 | G69: .1019278
A70: 223 | B70: 19951 | C70: .0340207 | D70: .0686004 | E70: .0102137 | F70: .040839 | G70: .1291245
A71: 223 | B71: 19952 | C71: .0084591 | D71: .0630971 | E71: -.0003891 | F71: .0393857 | G71: .1741788
A72: 223 | B72: 19953 | C72: -.0111025 | D72: -.0324062 | E72: .0070081 | F72: .0355326 | G72: .140343
A73: 223 | B73: 19954 | C73: -.009664 | D73: -.0539095 | E73: .0124052 | F73: .038806 | G73: .1308381
A74: 223 | B74: 19961 | C74: -.0112256 | D74: -.0894128 | E74: .0208024 | F74: .0301179 | G74: .1193185
A75: 223 | B75: 19962 | C75: -.0017872 | D75: -.0609161 | E75: .0101996 | F75: .0332429 | G75: .1139008
A76: 223 | B76: 19963 | C76: .0266512 | D76: -.0124194 | E76: -.0024032 | F76: .0381779 | G76: .1050886
A77: 223 | B77: 19964 | C77: .0190896 | D77: .0030773 | E77: -.008006 | F77: .0335721 | G77: .0848354
A78: 223 | B78: 19971 | C78: .012528 | D78: .003574 | E78: -.0016089 | F78: .0328583 | G78: .0838366
A79: 223 | B79: 19972 | C79: .0199665 | D79: .0250707 | E79: -.0022117 | F79: .0369045 | G79: .0824513
... A97: 223 | B97: 20014 | C97: -.021142 | D97: -.0219886 | E97: .0109375 | F97: -.0006314 | G97: .1111783
A98: 248 | B98: 19941 | C98: -.0397557 | D98: .0000568 | E98: .0113125 | F98: .007174
A99: 248 | B99: 19942 | C99: -.0342694 | D99: .008904 | E99: -.0062016 | F99: .0192438
A100: 248 | B100: 19943 | C100: -.0087832 | D100: .0017511 | E100: .0072843 | F100: .0254314
A101: 248 | B101: 19944 | C101: -.0022969 | D101: .0265982 | E101: .0057702 | F101: .0320287
A102: 248 | B102: 19951 | C102: -.0138107 | D102: -.0195546 | E102: -.019744 | F102: .040839
A103: 248 | B103: 19952 | C103: .0136756 | D103: -.0207075 | E103: -.0102581 | F103: .0393857 | G103: .222457
A104: 248 | B104: 19953 | C104: -.0078382 | D104: .0141397 | E104: -.0267722 | F104: .0355326 | G104: .1804984
A105: 248 | B105: 19954 | C105: -.0073519 | D105: .0079868 | E105: -.0092863 | F105: .038806 | G105: .187226
A106: 248 | B106: 19961 | C106: .0041343 | D106: -.0081661 | E106: .0121996 | F106: .0301179 | G106: .1716174
A107: 248 | B107: 19962 | C107: .0056206 | D107: -.0153189 | E107: .0336855 | F107: .0332429 | G107: .1543094
A108: 248 | B108: 19963 | C108: .0091069 | D108: -.0244718 | E108: .0571714 | F108: .0381779 | G108: .1459555
A109: 248 | B109: 19964 | C109: .0195931 | D109: -.0286246 | E109: .0596573 | F109: .0335721 | G109: .1221323
A110: 248 | B110: 19971 | C110: .0270794 | D110: .0422225 | E110: -.0108569 | F110: .0328583 | G110: .1018245
A111: 248 | B111: 19972 | C111: .0405656 | D111: .0840696 | E111: -.020371 | F111: .0369045 | G111: .1185766
A112: 248 | B112: 19973 | C112: .0410519 | D112: .0929168 | E112: -.0248851 | F112: .0350084 | G112: .0977015
A113: 248 | B113: 19974 | C113: .0395381 | D113: .0697639 | E113: -.0243992 | F113: .0349282 | G113: .0830515
A114: 248 | B114: 19981 | C114: .0380244 | D114: .1326111 | E114: -.0659133 | F114: .0353035 | G114: .0980905
... A161: 273 | B161: 20014 | C161: -.0307273 | D161: -.1316591 | E161: -.0061648 | F161: -.0006314 | G161: .0420449
A162: 293 | B162: 19941 | C162: -.0896193 | D162: -.2577159 | E162: .0197045 | F162: .007174
A163: 293 | B163: 19942 | C163: -.0665027 | D163: -.2338209 | E163: .0225482 | F163: .0192438
A164: 293 | B164: 19943 | C164: -.0283862 | D164: -.102926 | E164: .0263919 | F164: .0254314
A165: 293 | B165: 19944 | C165: .0057304 | D165: -.054031 | E165: .0092355 | F165: .0320287
A166: 293 | B166: 19951 | C166: .016847 | D166: .065864 | E166: -.0059208 | F166: .040839
A167: 293 | B167: 19952 | C167: .0049635 | D167: .086759 | E167: -.0090772 | F167: .0393857
A168: 293 | B168: 19953 | C168: .0160801 | D168: .052654 | E168: -.0102335 | F168: .0355326
A169: 293 | B169: 19954 | C169: .0061967 | D169: .0115489 | E169: -.0093898 | F169: .038806
A170: 293 | B170: 19961 | C170: -.0006868 | D170: -.0205561 | E170: .0054538 | F170: .0301179
A171: 293 | B171: 19962 | C171: .0034298 | D171: -.0096611 | E171: -.0087025 | F171: .0332429
A172: 293 | B172: 19963 | C172: .0125464 | D172: .0022339 | E172: -.0128589 | F172: .0381779
A173: 293 | B173: 19964 | C173: .0186629 | D173: .0351289 | E173: -.0060152 | F173: .0335721
A174: 293 | B174: 19971 | C174: .0337795 | D174: .0790238 | E174: .0058284 | F174: .0328583
A175: 293 | B175: 19972 | C175: .0558961 | D175: .0939188 | E175: .0066721 | F175: .0369045 | G175: .082069
A176: 293 | B176: 19973 | C176: .0460126 | D176: .1328138 | E176: -.0144842 | F176: .0350084 | G176: .0683465
A177: 293 | B177: 19974 | C177: .0471292 | D177: .1737088 | E177: -.0176406 | F177: .0349282 | G177: .0685564
A178: 293 | B178: 19981 | C178: .0282458 | D178: .1156037 | E178: -.0347969 | F178: .0353035 | G178: .0765414
A179: 293 | B179: 19982 | C179: .0003624 | D179: .1234987 | E179: -.0289533 | F179: .0394662 | G179: .0777249
A180: 293 | B180: 19983 | C180: .0284789 | D180: .1103937 | E180: -.0171096 | F180: .0447387 | G180: .0977106
A181: 293 | B181: 19984 | C181: -.0034045 | D181: .0612887 | E181: .0037341 | F181: .0334067 | G181: .1179316
A182: 293 | B182: 19991 | C182: -.0032879 | D182: -.0068163 | E182: .0105777 | F182: .0328529 | G182: .0922532
A183: 293 | B183: 19992 | C183: -.0161714 | D183: .0150786 | E183: .0064214 | F183: .0333959 | G183: .0857037
A184: 293 | B184: 19993 | C184: -.0120548 | D184: .0379736 | E184: .007265 | F184: .0375427 | G184: .0963775
A185: 293 | B185: 19994 | C185: .0130618 | D185: .0428686 | E185: .0031087 | F185: .0377168 | G185: .0990941
A186: 293 | B186: 20001 | C186: .0191783 | D186: .0527636 | E186: .0069523 | F186: .0386172 | G186: .0802388
... A193: 293 | B193: 20014 | C193: -.0270057 | D193: -.1309716 | E193: .011858 | F193: -.0006314 | G193: .0643133
A194: 299 | B194: 19941 | C194: -.0171761 | F194: .007174 | G194: .0666685
A195: 299 | B195: 19942 | C195: -.0006668 | F195: .0192438 | G195: .1556087
A196: 299 | B196: 19943 | C196: -.0491574 | F196: .0254314 | G196: .1844843
A197: 299 | B197: 19944 | C197: -.0316481 | F197: .0320287 | G197: .1634078
A198: 299 | B198: 19951 | C198: -.0021387 | F198: .040839 | G198: .2087235
A199: 299 | B199: 19952 | C199: -.0056294 | F199: .0393857 | G199: .2326472
A200: 299 | B200: 19953 | C200: .0148799 | F200: .0355326 | G200: .1977365
A201: 299 | B201: 19954 | C201: .0093893 | F201: .038806 | G201: .1995634
A202: 299 | B202: 19961 | C202: -.0061014 | F202: .0301179 | G202: .1723117
A203: 299 | B203: 19962 | C203: -.024592 | F203: .0332429 | G203: .1538663
A204: 299 | B204: 19963 | C204: -.0080827 | F204: .0381779 | G204: .1318504
A205: 299 | B205: 19964 | C205: .0054267 | F205: .0335721 | G205: .0908027
... A225: 299 | B225: 20014 | C225: -.0013864 | F225: -.0006314 | G225: .0955874
A226: 566 | B226: 19941 | C226: -.0195739 | D226: -.1401932 | E226: .0439602 | F226: .007174
A227: 566 | B227: 19942 | C227: -.0202445 | D227: .0314806 | E227: .0414144 | F227: .0192438
A228: 566 | B228: 19943 | C228: -.0289151 | D228: -.0878457 | E228: .0308686 | F228: .0254314
A229: 566 | B229: 19944 | C229: -.0005858 | D229: -.0601719 | E229: .0433228 | F229: .0320287
A230: 566 | B230: 19951 | C230: -.0072564 | D230: -.0834982 | E230: .0207769 | F230: .040839
A231: 566 | B231: 19952 | C231: -.0129271 | D231: -.0908244 | E231: .0032311 | F231: .0393857
...

Sheet BR_extended
A1: time | B1: logydsa | C1: loginvdsa | D1: tbysa | E1: logrus | F1: logi
A2: 19941 | E2: =logRus!G6 -> 0.013200219 | F2: =Brazil_interest!J2 -> 0.13029652
A3: 19942 | E3: =logRus!G7 -> 0.020667612 | F3: =Brazil_interest!J3 -> 0.1368833
A4: 19943 | E4: =logRus!G8 -> 0.025664052 | F4: =Brazil_interest!J4 -> 0.1019278
A5: 19944 | E5: =logRus!G9 -> 0.03528647 | F5: =Brazil_interest!J5 -> 0.1291245
A6: 19951 | E6: =logRus!G10 -> 0.036067622 | F6: =Brazil_interest!J6 -> 0.1741788
A7: 19952 | E7: =logRus!G11 -> 0.03353997 | F7: =Brazil_interest!J7 -> 0.140343
A8: 19953 | E8: =logRus!G12 -> 0.032355006 | F8: =Brazil_interest!J8 -> 0.1308381
A9: 19954 | E9: =logRus!G13 -> 0.031628384 | F9: =Brazil_interest!J9 -> 0.1193185
A10: 19961 | B10: =PIB!G2 -> -0.054735166 | C10: =INV!G2 -> -0.051711441 | D10: ='balança comercial_bens'!E6 -> 0.0038486536 | E10: =logRus!G14 -> 0.030429714 | F10: =Brazil_interest!J10 -> 0.1139008
A11: 19962 | B11: =PIB!G3 -> -0.048373709 | C11: =INV!G3 -> -0.037742761 | D11: ='balança comercial_bens'!E7 -> -0.0072933027 | E11: =logRus!G15 -> 0.032328428 | F11: =Brazil_interest!J11 -> 0.1050886
A12: 19963 | B12: =PIB!G4 -> -0.017696821 | C12: =INV!G4 -> -0.0061021024 | D12: ='balança comercial_bens'!E8 -> -0.0097134117 | E12: =logRus!G16 -> 0.034068247 | F12: =Brazil_interest!J12 -> 0.0848354
A13: 19964 | B13: =PIB!G5 -> -0.032771176 | C13: =INV!G5 -> 0.03052673 | D13: ='balança comercial_bens'!E9 -> -0.017304247 | E13: =logRus!G17 -> 0.031642035 | F13: =Brazil_interest!J13 -> 0.0838366
A14: 19971 | B14: =PIB!G6 -> -0.027623242 | C14: =INV!G6 -> 0.033762506 | D14: ='balança comercial_bens'!E10 -> 0.0022336593 | E14: =logRus!G18 -> 0.032776734 | F14: =Brazil_interest!J14 -> 0.0824513
A15: 19972 | B15: =PIB!G7 -> -0.02838486 | C15: =INV!G7 -> 0.042622257 | D15: ='balança comercial_bens'!E11 -> -0.01391199 | E15: =logRus!G19 -> 0.03292556 | F15: =Brazil_interest!J15 -> 0.0733634
A16: 19973 | B16: =PIB!G8 -> -0.021233384 | C16: =INV!G8 -> 0.056872329 | D16: ='balança comercial_bens'!E12 -> -0.011390055 | E16: =logRus!G20 -> 0.031932466 | F16: =Brazil_interest!J16 -> 0.0701023
A17: 19974 | B17: =PIB!G9 -> -0.018431453 | C17: =INV!G9 -> 0.045136801 | D17: ='balança comercial_bens'!E13 -> -0.011685763 | E17: =logRus!G21 -> 0.036029588 | F17: =Brazil_interest!J17 -> 0.0860917
A18: 19981 | B18: =PIB!G10 -> -0.043951356 | C18: =INV!G10 -> 0.045389159 | D18: ='balança comercial_bens'!E14 -> -0.0029077692 | E18: =logRus!G22 -> 0.039224206 | F18: =Brazil_interest!J18 -> 0.0832917
A19: 19982 | B19: =PIB!G11 -> -0.032404693 | C19: =INV!G11 -> 0.043911652 | D19: ='balança comercial_bens'!E15 -> -0.0077125933 | E19: =logRus!G23 -> 0.038471198 | F19: =Brazil_interest!J19 -> 0.1073378
A20: 19983 | B20: =PIB!G12 -> -0.038317208 | C20: =INV!G12 -> 0.025769352 | D20: ='balança comercial_bens'!E16 -> -0.012213057 | E20: =logRus!G24 -> 0.03497643 | F20: =Brazil_interest!J20 -> 0.1681124
A21: 19984 | B21: =PIB!G13 -> -0.055343181 | C21: =INV!G13 -> -0.025450091 | D21: ='balança comercial_bens'!E17 -> -0.012502646 | E21: =logRus!G25 -> 0.033195265 | F21: =Brazil_interest!J21 -> 0.1489456
... A29: 20004 | B29: =PIB!G21 -> -0.030055393 | C29: =INV!G21 -> -0.036381619 | D29: ='balança comercial_bens'!E25 -> -0.0087100261 | E29: =logRus!G33 -> 0.033659557 | F29: =Brazil_interest!J29 -> 0.1126679
A30: =A26+10 -> 20011 | B30: =PIB!G22 -> -0.031978116 | C30: =INV!G22 -> -0.024353999 | D30: ='balança comercial_bens'!E26 -> 0.00037633381 | E30: =logRus!G34 -> 0.020403536 | F30: =Brazil_interest!J30 -> 0.1001101
A31: =A30+1 -> 20012 | B31: =PIB!G23 -> -0.042280639 | C31: =INV!G23 -> -0.055494087 | D31: ='balança comercial_bens'!E27 -> -0.0042437699 | E31: =logRus!G35 -> 0.011286791 | F31: =Brazil_interest!J31 -> 0.1009832
A32: =A31+1 -> 20013 | B32: =PIB!G24 -> -0.053139304 | C32: =INV!G24 -> -0.074890651 | D32: ='balança comercial_bens'!E28 -> 0.004630367 | E32: =logRus!G36 -> 0.0046637518 | F32: =Brazil_interest!J32 -> 0.1111783
A33: =A32+1 -> 20014 | B33: =PIB!G25 -> -0.061437489 | C33: =INV!G25 -> -0.13762284 | D33: ='balança comercial_bens'!E29 -> 0.0097659607 | E33: =logRus!G37 -> -0.0025796958 | F33: =Brazil_interest!J33 -> 0.084045089
A34: =A30+10 -> 20021 | B34: =PIB!G26 -> -0.042491747 | C34: =INV!G26 -> -0.13076008 | D34: ='balança comercial_bens'!E30 -> 0.013969593 | E34: =logRus!G38 -> 0.0019374655 | F34: =Brazil_interest!J34 -> 0.10399131
A35: =A34+1 -> 20022 | B35: =PIB!G27 -> -0.04585715 | C35: =INV!G27 -> -0.11288088 | D35: ='balança comercial_bens'!E31 -> 0.0032363348 | E35: =logRus!G39 -> 0.0034667722 | F35: =Brazil_interest!J35 -> 0.18365743
A36: =A35+1 -> 20023 | B36: =PIB!G28 -> -0.037515107 | C36: =INV!G28 -> -0.10252671 | D36: ='balança comercial_bens'!E32 -> 0.035358237 | E36: =logRus!G40 -> 0.0019256585 | F36: =Brazil_interest!J36 -> 0.16777828
A37: =A36+1 -> 20024 | B37: =PIB!G29 -> -0.032831641 | C37: =INV!G29 -> -0.086624814 | D37: ='balança comercial_bens'!E33 -> 0.039843278 | E37: =logRus!G41 -> -0.0051657955 | F37: =Brazil_interest!J37 -> 0.11920451
A38: =A34+10 -> 20031 | B38: =PIB!G30 -> -0.042871372 | C38: =INV!G30 -> -0.12181285 | D38: ='balança comercial_bens'!E34 -> 0.038559469 | E38: =logRus!G42 -> -0.0074965143 | F38: =Brazil_interest!J38 -> 0.076964508
A39: =A38+1 -> 20032 | B39: =PIB!G31 -> -0.056872858 | C39: =INV!G31 -> -0.19911122 | D39: ='balança comercial_bens'!E35 -> 0.038750536 | E39: =logRus!G43 -> -0.0096020533 | F39: =Brazil_interest!J39 -> 0.071629937
A40: =A39+1 -> 20033 | B40: =PIB!G32 -> -0.053011578 | C40: =INV!G32 -> -0.19759342 | D40: ='balança comercial_bens'!E36 -> 0.04486792 | E40: =logRus!G44 -> -0.010329787 | F40: =Brazil_interest!J40 -> 0.05404138
A41: =A40+1 -> 20034 | B41: =PIB!G33 -> -0.048143041 | C41: =INV!G33 -> -0.1586997 | D41: ='balança comercial_bens'!E37 -> 0.043941463 | E41: =logRus!G45 -> -0.011114891 | F41: =Brazil_interest!J41 -> 0.050541763
A42: =A38+10 -> 20041 | B42: =PIB!G34 -> -0.040055004 | C42: =INV!G34 -> -0.1323319 | D42: ='balança comercial_bens'!E38 -> 0.045651018 | E42: =logRus!G46 -> -0.012947136 | F42: =Brazil_interest!J42 -> 0.064462014
A43: =A42+1 -> 20042 | B43: =PIB!G35 -> -0.01840059 | C43: =INV!G35 -> -0.1038947 | D43: ='balança comercial_bens'!E39 -> 0.047191687 | E43: =logRus!G47 -> -0.014108947 | F43: =Brazil_interest!J43 -> 0.053660893
A44: =A43+1 -> 20043 | B44: =PIB!G36 -> -0.01125284 | C44: =INV!G36 -> -0.088974251 | D44: ='balança comercial_bens'!E40 -> 0.054159511 | E44: =logRus!G48 -> -0.010890811 | F44: =Brazil_interest!J44 -> 0.046982482
A45: =A44+1 -> 20044 | B45: =PIB!G37 -> -0.0091609437 | C45: =INV!G37 -> -0.11091138 | D45: ='balança comercial_bens'!E41 -> 0.045815645 | E45: =logRus!G49 -> -0.0072407313 | F45: =Brazil_interest!J45 -> 0.048289447
A46: =A42+10 -> 20051 | B46: =PIB!G38 -> -0.0058703448 | C46: =INV!G38 -> -0.13592999 | D46: ='balança comercial_bens'!E42 -> 0.050833649 | E46: =logRus!G50 -> -0.0024203023 | F46: =Brazil_interest!J46 -> 0.051629777
A47: =A46+1 -> 20052 | B47: =PIB!G39 -> -0.0011022832 | C47: =INV!G39 -> -0.093622136 | D47: ='balança comercial_bens'!E43 -> 0.04514481 | E47: =logRus!G51 -> 0.00076734801 | F47: =Brazil_interest!J47 -> 0.052923048
A48: =A47+1 -> 20053 | B48: =PIB!G40 -> -0.012248737 | C48: =INV!G40 -> -0.10431136 | D48: ='balança comercial_bens'!E44 -> 0.051245923 | E48: =logRus!G52 -> 0.0023780678 | F48: =Brazil_interest!J48 -> 0.049684641
A49: =A48+1 -> 20054 | B49: =PIB!G41 -> -0.0052119484 | C49: =INV!G41 -> -0.10794898 | D49: ='balança comercial_bens'!E45 -> 0.048192399 | E49: =logRus!G53 -> 0.0065474518 | F49: =Brazil_interest!J49 -> 0.046149614
A50: =A46+10 -> 20061 | B50: =PIB!G42 -> 0.0053947723 | C50: =INV!G42 -> -0.067785012 | D50: ='balança comercial_bens'!E46 -> 0.043297916 | E50: =logRus!G54 -> 0.013763886 | F50: =Brazil_interest!J50 -> 0.049546222
A51: =A50+1 -> 20062 | B51: =PIB!G43 -> 0.0028124631 | C51: =INV!G43 -> -0.077220357 | D51: ='balança comercial_bens'!E47 -> 0.03024505 | E51: =logRus!G55 -> 0.015017918 | F51: =Brazil_interest!J51 -> 0.047001962
A52: =A51+1 -> 20063 | B52: =PIB!G44 -> 0.013860743 | C52: =INV!G44 -> -0.072990468 | D52: ='balança comercial_bens'!E48 -> 0.047478583 | E52: =logRus!G56 -> 0.017230085 | F52: =Brazil_interest!J52 -> 0.048480227
A53: =A52+1 -> 20064 | B53: =PIB!G45 -> 0.019940797 | C53: =INV!G45 -> -0.04769805 | D53: ='balança comercial_bens'!E49 -> 0.04146069 | E53: =logRus!G57 -> 0.022212117 | F53: =Brazil_interest!J53 -> 0.050680535
A54: =A50+10 -> 20071 | B54: =PIB!G46 -> 0.033134352 | C54: =INV!G46 -> -0.014782602 | D54: ='balança comercial_bens'!E50 -> 0.03580201 | E54: =logRus!G58 -> 0.020860476 | F54: =Brazil_interest!J54 -> 0.041404857
A55: =A54+1 -> 20072 | B55: =PIB!G47 -> 0.044138587 | C55: =INV!G47 -> 0.021998074 | D55: ='balança comercial_bens'!E51 -> 0.027450186 | E55: =logRus!G59 -> 0.019384958 | F55: =Brazil_interest!J55 -> 0.040765671
A56: =A55+1 -> 20073 | B56: =PIB!G48 -> 0.048916424 | C56: =INV!G48 -> 0.035900303 | D56: ='balança comercial_bens'!E52 -> 0.02480631 | E56: =logRus!G60 -> 0.013709908 | F56: =Brazil_interest!J56 -> 0.037120518
A57: =A56+1 -> 20074 | B57: =PIB!G49 -> 0.058447687 | C57: =INV!G49 -> 0.056452349 | D57: ='balança comercial_bens'!E53 -> 0.023461349 | E57: =logRus!G61 -> 0.0043552009 | F57: =Brazil_interest!J57 -> 0.026586483
A58: =A54+10 -> 20081 | B58: =PIB!G50 -> 0.065569737 | C58: =INV!G50 -> 0.081594824 | D58: ='balança comercial_bens'!E54 -> 0.013258492 | E58: =logRus!G62 -> -0.0074011638 | F58: =Brazil_interest!J58 -> 0.0328314
A59: =A58+1 -> 20082 | B59: =PIB!G51 -> 0.07979942 | C59: =INV!G51 -> 0.13268206 | D59: ='balança comercial_bens'!E55 -> 0.011183876 | E59: =logRus!G63 -> 0.00070607568 | F59: =Brazil_interest!J59 -> 0.030426983
A60: =A59+1 -> 20083 | B60: =PIB!G52 -> 0.090616991 | C60: =INV!G52 -> 0.17786033 | D60: ='balança comercial_bens'!E56 -> 0.013750273 | E60: =logRus!G64 -> -0.0086427457 | F60: =Brazil_interest!J60 -> 0.038081134
A61: =A60+1 -> 20084 | B61: =PIB!G53 -> 0.046628139 | C61: =INV!G53 -> 0.086100796 | D61: ='balança comercial_bens'!E57 -> 0.016335902 | E61: =logRus!G65 -> -0.018152364 | F61: =Brazil_interest!J61 -> 0.03780173
A62: =A58+10 -> 20091 | B62: =PIB!G54 -> 0.026594042 | C62: =INV!G54 -> -0.036018736 | D62: ='balança comercial_bens'!E58 -> 0.016446036 | E62: =logRus!G66 -> -0.011758993 | F62: =Brazil_interest!J62 -> 0.030948119
A63: =A62+1 -> 20092 | B63: =PIB!G55 -> 0.039382336 | C63: =INV!G55 -> 0.027904793 | D63: ='balança comercial_bens'!E59 -> 0.022008002 | E63: =logRus!G67 -> -0.0056708675 | F63: =Brazil_interest!J63 -> 0.02982061
A64: =A63+1 -> 20093 | B64: =PIB!G56 -> 0.056923752 | C64: =INV!G56 -> 0.11671769 | D64: ='balança comercial_bens'!E60 -> 0.012863043 | E64: =logRus!G68 -> 4.6902777e-05 | F64: =Brazil_interest!J64 -> 0.032080711
A65: =A64+1 -> 20094 | B65: =PIB!G57 -> 0.076875238 | C65: =INV!G57 -> 0.18501226 | D65: ='balança comercial_bens'!E61 -> 0.0095980278 | E65: =logRus!G69 -> -0.0013869134 | F65: =Brazil_interest!J65 -> 0.030710885
A66: =A62+10 -> 20101 | B66: =PIB!G58 -> 0.091679016 | C66: =INV!G58 -> 0.19918203 | D66: ='balança comercial_bens'!E62 -> 0.0083420613 | E66: =logRus!G70 -> -0.0040602355 | F66: =Brazil_interest!J66 -> 0.030266504
A67: =A66+1 -> 20102 | B67: =PIB!G59 -> 0.098867854 | C67: =INV!G59 -> 0.21404789 | D67: ='balança comercial_bens'!E63 -> 0.0058459959 | E67: =logRus!G71 -> -0.010885739 | F67: =Brazil_interest!J67 -> 0.025260291
A68: =A67+1 -> 20103 | B68: =PIB!G60 -> 0.10209955 | C68: =INV!G60 -> 0.23910949 | D68: ='balança comercial_bens'!E64 -> 0.0047857764 | E68: =logRus!G72 -> -0.012435425 | F68: =Brazil_interest!J68 -> 0.018069081
A69: =A68+1 -> 20104 | B69: =PIB!G61 -> 0.11074259 | C69: =INV!G61 -> 0.2392047 | D69: ='balança comercial_bens'!E65 -> 0.013239357 | E69: =logRus!G73 -> -0.015165934 | F69: =Brazil_interest!J69 -> 0.015066374
A70: =A66+10 -> 20111 | B70: =PIB!G62 -> 0.11845943 | C70: =INV!G62 -> 0.25584541 | D70: ='balança comercial_bens'!E66 -> 0.011510533 | E70: =logRus!G74 -> -0.017804081 | F70: =Brazil_interest!J70 -> 0.013943154
A71: =A70+1 -> 20112 | B71: =PIB!G63 -> 0.12306391 | C71: =INV!G63 -> 0.27060201 | D71: ='balança comercial_bens'!E67 -> 0.0069685549 | E71: =logRus!G75 -> -0.020129755 | F71: =Brazil_interest!J71 -> 0.014729192
A72: =A71+1 -> 20113 | B72: =PIB!G64 -> 0.11530086 | C72: =INV!G64 -> 0.27755079 | D72: ='balança comercial_bens'!E68 -> 0.01114777 | E72: =logRus!G76 -> -0.023393876 | F72: =Brazil_interest!J72 -> 0.015637657
A73: =A72+1 -> 20114 | B73: =PIB!G65 -> 0.1187524 | C73: =INV!G65 -> 0.27287887 | D73: ='balança comercial_bens'!E69 -> 0.01175123 | E73: =logRus!G77 -> -0.018796228 | F73: =Brazil_interest!J73 -> 0.017037022
A74: =A70+10 -> 20121 | B74: =PIB!G66 -> 0.098912906 | C74: =INV!G66 -> 0.26220492 | D74: ='balança comercial_bens'!E70 -> 0.010126038 | E74: =logRus!G78 -> -0.018831621 | F74: =Brazil_interest!J74 -> 0.016747617
A75: =A74+1 -> 20122 | B75: =PIB!G67 -> 0.11130902 | C75: =INV!G67 -> 0.25964727 | D75: ='balança comercial_bens'!E71 -> 0.00014076652 | E75: =logRus!G79 -> -0.016256289 | F75: =Brazil_interest!J75 -> 0.016345255
A76: =A75+1 -> 20123 | B76: =PIB!G68 -> 0.12274647 | C76: =INV!G68 -> 0.24585198 | D76: ='balança comercial_bens'!E72 -> 0.01037729 | E76: =logRus!G80 -> -0.015529691 | F76: =Brazil_interest!J76 -> 0.014467387
A77: =A76+1 -> 20124 | B77: =PIB!G69 -> 0.11755899 | C77: =INV!G69 -> 0.25998565 | D77: ='balança comercial_bens'!E73 -> 0.007038142 | E77: =logRus!G81 -> -0.019745548 | F77: =Brazil_interest!J77 -> 0.013693469
A78: =A74+10 -> 20131 | B78: =PIB!G70 -> 0.11743971 | C78: =INV!G70 -> 0.26632197 | D78: ='balança comercial_bens'!E74 -> -0.0016830057 | E78: =logRus!G82 -> -0.017656375 | F78: =Brazil_interest!J78 -> 0.015203346
A79: =A78+1 -> 20132 | B79: =PIB!G71 -> 0.12546486 | C79: =INV!G71 -> 0.31898113 | D79: ='balança comercial_bens'!E75 -> -0.0041306773 | E79: =logRus!G83 -> -0.016089783 | F79: =Brazil_interest!J79 -> 0.014515139
A80: =A79+1 -> 20133 | B80: =PIB!G72 -> 0.12473063 | C80: =INV!G72 -> 0.29974319 | D80: ='balança comercial_bens'!E76 -> -0.0016676268 | E80: =logRus!G84 -> -0.015807341 | F80: =Brazil_interest!J80 -> 0.016330255
A81: =A80+1 -> 20134 | B81: =PIB!G73 -> 0.12078871 | C81: =INV!G73 -> 0.28425197 | D81: ='balança comercial_bens'!E77 -> 0.0080437533 | E81: =logRus!G85 -> -0.015572292 | F81: =Brazil_interest!J81 -> 0.014891601
A82: =A78+10 -> 20141 | B82: =PIB!G74 -> 0.12358897 | C82: =INV!G74 -> 0.282466 | D82: ='balança comercial_bens'!E78 -> -0.0035124719 | E82: =logRus!G86 -> -0.015603138 | F82: =Brazil_interest!J82 -> 0.014048713
A83: =A82+1 -> 20142 | B83: =PIB!G75 -> 0.10325518 | C83: =INV!G75 -> 0.23240699 | D83: ='balança comercial_bens'!E79 -> -0.0021361798 | E83: =logRus!G87 -> -0.019196661 | F83: =Brazil_interest!J83 -> 0.013759984
A84: =A83+1 -> 20143 | B84: =PIB!G76 -> 0.097143634 | C84: =INV!G76 -> 0.20360982 | D84: ='balança comercial_bens'!E80 -> -0.001298555 | E84: =logRus!G88 -> -0.018602677 | F84: =Brazil_interest!J84 -> 0.015063234
A85: =A84+1 -> 20144 | B85: =PIB!G77 -> 0.096811953 | C85: =INV!G77 -> 0.19653902 | D85: ='balança comercial_bens'!E81 -> -0.0050771044 | E85: =logRus!G89 -> -0.014226074 | F85: =Brazil_interest!J85 -> 0.019152139
A86: =A82+10 -> 20151 | B86: =PIB!G78 -> 0.083252738 | C86: =INV!G78 -> 0.1603722 | D86: ='balança comercial_bens'!E82 -> -0.0042091762 | E86: =logRus!G90 -> -0.0098916425 | F86: =Brazil_interest!J86 -> 0.020157032
A87: =A86+1 -> 20152 | B87: =PIB!G79 -> 0.053964989 | C87: =INV!G79 -> 0.083262315 | D87: ='balança comercial_bens'!E83 -> 0.0082570803 | E87: =logRus!G91 -> -0.010073119 | F87: =Brazil_interest!J87 -> 0.024448345
A88: =A87+1 -> 20153 | B88: =PIB!G80 -> 0.031795488 | C88: =INV!G80 -> 0.020364722 | D88: ='balança comercial_bens'!E84 -> 0.015165314 | E88: =logRus!G92 -> -0.0086245614 | F88: =Brazil_interest!J88 -> 0.025782571
A89: =A88+1 -> 20154 | B89: =PIB!G81 -> 0.018561354 | C89: =INV!G81 -> -0.039467021 | D89: ='balança comercial_bens'!E85 -> 0.023813852 | E89: =logRus!G93 -> -0.0055087766 | F89: =Brazil_interest!J89 -> 0.021654334
A90: =A86+10 -> 20161 | B90: =PIB!G82 -> -0.0013847164 | C90: =INV!G82 -> -0.067623457 | D90: ='balança comercial_bens'!E86 -> 0.028426766 | E90: =logRus!G94 -> -0.0044901357 | F90: =Brazil_interest!J90 -> 0.019897075
A91: =A90+1 -> 20162 | B91: =PIB!G83 -> -0.004293236 | C91: =INV!G83 -> -0.047883352 | D91: ='balança comercial_bens'!E87 -> 0.025855577 | E91: =logRus!G95 -> -0.0058348764 | F91: =Brazil_interest!J91 -> 0.018584584
A92: =A91+1 -> 20163 | B92: =PIB!G84 -> -0.015158792 | C92: =INV!G84 -> -0.11558519 | D92: ='balança comercial_bens'!E88 -> 0.02105043 | E92: =logRus!G96 -> -0.0055410394 | F92: =Brazil_interest!J92 -> 0.018238447
A93: =A92+1 -> 20164 | B93: =PIB!G85 -> -0.021864136 | C93: =INV!G85 -> -0.13967019 | D93: ='balança comercial_bens'!E89 -> 0.023592699 | E93: =logRus!G97 -> -0.0082054978 | F93: =Brazil_interest!J93 -> 0.016458208
A94: =A90+10 -> 20171 | B94: =PIB!G86 -> -0.017128161 | C94: =INV!G86 -> -0.14115979 | D94: ='balança comercial_bens'!E90 -> 0.033537316 | E94: =logRus!G98 -> -0.011769348 | F94: =Brazil_interest!J94 -> 0.016522103
A95: =A94+1 -> 20172 | B95: =PIB!G87 -> -0.014305098 | C95: =INV!G87 -> -0.14653693 | D95: ='balança comercial_bens'!E91 -> 0.031028703 | E95: =logRus!G99 -> -0.0051268254 | F95: =Brazil_interest!J95 -> 0.01734352
A96: =A95+1 -> 20173 | B96: =PIB!G88 -> -0.017673465 | C96: =INV!G88 -> -0.14767435 | D96: ='balança comercial_bens'!E92 -> 0.024367171 | E96: =logRus!G100 -> -0.0072028443 | F96: =Brazil_interest!J96 -> 0.016060977
A97: =A96+1 -> 20174 | B97: =PIB!G89 -> -0.017807758 | C97: =INV!G89 -> -0.1223011 | D97: ='balança comercial_bens'!E93 -> 0.022627029 | E97: =logRus!G101 -> -0.0056398833 | F97: =Brazil_interest!J97 -> 0.01707037
A98: =A94+10 -> 20181 | B98: =PIB!G90 -> -0.017137613 | C98: =INV!G90 -> -0.12823712 | D98: ='balança comercial_bens'!E94 -> 0.025203023 | E98: =logRus!G102 -> -0.0030557062 | F98: =Brazil_interest!J98 -> 0.019563924
A99: =A98+1 -> 20182 | B99: =PIB!G91 -> -0.023926185 | C99: =INV!G91 -> -0.12676081 | D99: ='balança comercial_bens'!E95 -> 0.023272124 | E99: =logRus!G103 -> -0.0054296834 | F99: =Brazil_interest!J99 -> 0.018828655
A100: =A99+1 -> 20183 | B100: =PIB!G92 -> -0.019916954 | C100: =INV!G92 -> -0.080375288 | D100: ='balança comercial_bens'!E96 -> 0.015236993 | E100: =logRus!G104 -> -0.0023608942 | F100: =Brazil_interest!J100 -> 0.019022871
A101: =A100+1 -> 20184 | B101: =PIB!G93 -> -0.027936873 | C101: =INV!G93 -> -0.10319056 | D101: ='balança comercial_bens'!E97 -> 0.028912994 | E101: =logRus!G105 -> 0.0018239023 | F101: =Brazil_interest!J101 -> 0.019175684
A102: =A98+10 -> 20191 | B102: =PIB!G94 -> -0.03058009 | C102: =INV!G94 -> -0.12004325 | D102: ='balança comercial_bens'!E98 -> 0.018112508 | E102: =logRus!G106 -> 0.0055595254 | F102: =Brazil_interest!J102 -> 0.018372843
A103: =A102+1 -> 20192 | B103: =PIB!G95 -> -0.030294804 | C103: =INV!G95 -> -0.074433816 | D103: ='balança comercial_bens'!E99 -> 0.01954339 | E103: =logRus!G107 -> 0.0052002548 | F103: =Brazil_interest!J103 -> 0.017892738
A104: =A103+1 -> 20193 | B104: =PIB!G96 -> -0.035598316 | C104: =INV!G96 -> -0.0523708 | D104: ='balança comercial_bens'!E100 -> 0.0067227186 | E104: =logRus!G108 -> 0.0034928906 | F104: =Brazil_interest!J104 -> 0.01627399
A105: =A104+1 -> 20194 | B105: =PIB!G97 -> -0.03237927 | C105: =INV!G97 -> -0.11643624 | D105: ='balança comercial_bens'!E101 -> 0.018838143 | E105: =logRus!G109 -> 0.0011477482 | F105: =Brazil_interest!J105 -> 0.015881907
A106: =A102+10 -> 20201 | B106: =PIB!G98 -> -0.061144816 | C106: =INV!G98 -> -0.073305036 | D106: ='balança comercial_bens'!E102 -> 0.0072242792 | E106: =logRus!G110 -> -0.013045571 | F106: =Brazil_interest!J106 -> 0.016831844
A107: =A106+1 -> 20202 | B107: =PIB!G99 -> -0.15963404 | C107: =INV!G99 -> -0.25145092 | D107: ='balança comercial_bens'!E103 -> 0.037528588 | E107: =logRus!G111 -> -0.0055930848 | F107: =Brazil_interest!J107 -> 0.01836568
...

Sheet BR_extended_values
A1: time | B1: logydsa | C1: loginvdsa | D1: tbysa | E1: logrus | F1: logi
A2: 19941 | E2: 0.013200219 | F2: 0.13029652
A3: 19942 | E3: 0.020667612 | F3: 0.1368833
A4: 19943 | E4: 0.025664052 | F4: 0.1019278
A5: 19944 | E5: 0.03528647 | F5: 0.1291245
A6: 19951 | E6: 0.036067622 | F6: 0.1741788
A7: 19952 | E7: 0.03353997 | F7: 0.140343
A8: 19953 | E8: 0.032355006 | F8: 0.1308381
A9: 19954 | E9: 0.031628384 | F9: 0.1193185
A10: 19961 | B10: -0.054735166 | C10: -0.051711441 | D10: 0.0038486536 | E10: 0.030429714 | F10: 0.1139008
A11: 19962 | B11: -0.048373709 | C11: -0.037742761 | D11: -0.0072933027 | E11: 0.032328428 | F11: 0.1050886
A12: 19963 | B12: -0.017696821 | C12: -0.0061021024 | D12: -0.0097134117 | E12: 0.034068247 | F12: 0.0848354
A13: 19964 | B13: -0.032771176 | C13: 0.03052673 | D13: -0.017304247 | E13: 0.031642035 | F13: 0.0838366
A14: 19971 | B14: -0.027623242 | C14: 0.033762506 | D14: 0.0022336593 | E14: 0.032776734 | F14: 0.0824513
A15: 19972 | B15: -0.02838486 | C15: 0.042622257 | D15: -0.01391199 | E15: 0.03292556 | F15: 0.0733634
A16: 19973 | B16: -0.021233384 | C16: 0.056872329 | D16: -0.011390055 | E16: 0.031932466 | F16: 0.0701023
A17: 19974 | B17: -0.018431453 | C17: 0.045136801 | D17: -0.011685763 | E17: 0.036029588 | F17: 0.0860917
A18: 19981 | B18: -0.043951356 | C18: 0.045389159 | D18: -0.0029077692 | E18: 0.039224206 | F18: 0.0832917
A19: 19982 | B19: -0.032404693 | C19: 0.043911652 | D19: -0.0077125933 | E19: 0.038471198 | F19: 0.1073378
A20: 19983 | B20: -0.038317208 | C20: 0.025769352 | D20: -0.012213057 | E20: 0.03497643 | F20: 0.1681124
A21: 19984 | B21: -0.055343181 | C21: -0.025450091 | D21: -0.012502646 | E21: 0.033195265 | F21: 0.1489456
... A130: 20261 | B130: -0.033630359 | C130: -0.041473323 | D130: 0.026710436 | E130: 0.0044099428 | F130: 0.018344813

Sheet Spread
A1: Date | B1: Brazil, BLENDED SNRFOR CR 10Y PAR CDS Spread | C1: Brazil, BLENDED SNRFOR CR 5Y PAR CDS Spread
A3: 36892 | B3: 601.667 | C3: 502.5
A4: 36923 | B4: 635 | C4: 582.1
A5: 36951 | B5: 710 | C5: 628.125 | G5: 10y | H5: 5y | O5: slope (b) | P5: intercept (ln a) | Q5: a = EXP(ln a) | R5: R2
A6: 36982 | B6: 785 | C6: 711.25 | E6: =EDATE(F6,2) -> 36951 | F6: 36892 | G6: =VLOOKUP(E6,$A:$C,2,FALSE) -> 710 | H6: =VLOOKUP(E6,$A:$C,3,FALSE) -> 628.125 | O6: =INDEX(LINEST(K6:K53,J6:J53),1,1) -> #VALUE! | P6: =INDEX(LINEST(K6:K53,J6:J53),1,2) -> #VALUE! | Q6: =EXP(P6) -> #VALUE! | R6: =RSQ(K6:K53,J6:J53) -> #DIV/0!
A7: 37012 | B7: 821.667 | C7: 769.583 | E7: =EDATE(F7,2) -> 37043 | F7: 36982 | G7: =VLOOKUP(E7,$A:$C,2,FALSE) -> 844.375 | H7: =VLOOKUP(E7,$A:$C,3,FALSE) -> 775.583
A8: 37043 | B8: 844.375 | C8: 775.583 | E8: =EDATE(F8,2) -> 37135 | F8: 37073 | G8: =VLOOKUP(E8,$A:$C,2,FALSE) -> 1225.63 | H8: =VLOOKUP(E8,$A:$C,3,FALSE) -> 1176.88
A9: 37073 | B9: 975.625 | C9: 919.583 | E9: =EDATE(F9,2) -> 37226 | F9: 37165 | G9: =VLOOKUP(E9,$A:$C,2,FALSE) -> 893.75 | H9: =VLOOKUP(E9,$A:$C,3,FALSE) -> 824.583
A10: 37104 | B10: 961.875 | C10: 900.417 | E10: =EDATE(F10,2) -> 37316 | F10: 37257 | G10: =VLOOKUP(E10,$A:$C,2,FALSE) -> 768.357 | H10: =VLOOKUP(E10,$A:$C,3,FALSE) -> 718
A11: 37135 | B11: 1225.63 | C11: 1176.88 | E11: =EDATE(F11,2) -> 37408 | F11: 37347 | G11: =VLOOKUP(E11,$A:$C,2,FALSE) -> 1977.5 | H11: =VLOOKUP(E11,$A:$C,3,FALSE) -> 2193.75
A12: 37165 | B12: 1264.38 | C12: 1183.75 | E12: =EDATE(F12,2) -> 37500 | F12: 37438 | G12: =VLOOKUP(E12,$A:$C,2,FALSE) -> 3458.21 | H12: =VLOOKUP(E12,$A:$C,3,FALSE) -> 3733.36
A13: 37196 | B13: 1032.08 | C13: 960.417 | E13: =EDATE(F13,2) -> 37591 | F13: 37530 | G13: =VLOOKUP(E13,$A:$C,2,FALSE) -> 1880.75 | H13: =VLOOKUP(E13,$A:$C,3,FALSE) -> 2147
A14: 37226 | B14: 893.75 | C14: 824.583 | E14: =EDATE(F14,2) -> 37681 | F14: 37622 | G14: =VLOOKUP(E14,$A:$C,2,FALSE) -> 1346.19 | H14: =VLOOKUP(E14,$A:$C,3,FALSE) -> 1369.58
A15: 37257 | B15: 920 | C15: 852.083 | E15: =EDATE(F15,2) -> 37773 | F15: 37712 | G15: =VLOOKUP(E15,$A:$C,2,FALSE) -> 930.083 | H15: =VLOOKUP(E15,$A:$C,3,FALSE) -> 889.917
A16: 37288 | B16: 853.214 | C16: 791.071 | E16: =EDATE(F16,2) -> 37865 | F16: 37803 | G16: =VLOOKUP(E16,$A:$C,2,FALSE) -> 802.944 | H16: =VLOOKUP(E16,$A:$C,3,FALSE) -> 763
A17: 37316 | B17: 768.357 | C17: 718 | E17: =EDATE(F17,2) -> 37956 | F17: 37895 | G17: =VLOOKUP(E17,$A:$C,2,FALSE) -> 464.575 | H17: =VLOOKUP(E17,$A:$C,3,FALSE) -> 403.844
A18: 37347 | B18: 915.071 | C18: 861.857 | E18: =EDATE(F18,2) -> 38047 | F18: 37987 | G18: =VLOOKUP(E18,$A:$C,2,FALSE) -> 633.964 | H18: =VLOOKUP(E18,$A:$C,3,FALSE) -> 576.607
... A108: 40087 | B108: 162.893 | C108: 136.885 | E108: =EDATE(F108,2) -> 46266 | F108: 46204 | G108: =VLOOKUP(E108,$A:$C,2,FALSE) -> #N/A | H108: =VLOOKUP(E108,$A:$C,3,FALSE) -> #N/A
A109: 40118 | B109: 154.639 | C109: 129.533
A110: 40148 | B110: 145.591 | C110: 122.282
A111: 40179 | B111: 167.37 | C111: 142.862
A112: 40210 | B112: 152.006 | C112: 129.826
A113: 40238 | B113: 156.103 | C113: 131.062
A114: 40269 | B114: 147.272 | C114: 122.368
A115: 40299 | B115: 161.26 | C115: 136.112
A116: 40330 | B116: 164.876 | C116: 139.524
A117: 40360 | B117: 141.47 | C117: 116.64
A118: 40391 | B118: 156.753 | C118: 132.013
A119: 40422 | B119: 142.808 | C119: 116.067
A120: 40452 | B120: 129.577 | C120: 100.228
... A310: 46235 | B310: 207.194 | C310: 123.818
A311: Source | B311: Citi
A312: The information above, which may contain third party information, is confidential information of Citigroup Global Markets Inc., intended for the exclusive use of Citi Velocity customers, and not for distribution to any third parties for any purpose whatsoever. By accessing and using such information, you agree to (i) use it only for your internal analysis and other similar internal business purposes, (ii) not to transfer or disclose such information to any person, company or other entity, except to colleagues within your employer who have a need to know such information to carry out those internal business purposes, and (iii) destroy such information and any copies or duplicates as soon as your use thereof for those purposes has concluded. Your foregoing agreement is subject to the terms, conditions and exceptions relating to confidentiality contained in the Terms of Use of Citi Velocity, to which you have separately agreed.

Sheet Spread synthetic
A1: Date | B1: Source | C1: Ours_raw (pre-2001 only) | D1: Rus_gross_q | E1: Spread_%_annual (reconciled) | F1: R_gross_q | G1: R_hat (ln level) | I1: OLS a | J1: OLS b | K1: R2 (log-log)
A2: 34425 | B2: Pre-2001 (OLS-rescaled) | C2: 48.499784 | D2: 1.0040327 | E2: =$I$2*C2^$J$2 -> 13.469367 | F2: =D2+E2/400 -> 1.0377062 | G2: =LN(F2) -> 0.037012666 | I2: 0.069864899 | J2: 1.3555402 | K2: 0.95415963
A3: 34516 | B3: Pre-2001 (OLS-rescaled) | C3: 40.616217 | D3: 1.0056592 | E3: =$I$2*C3^$J$2 -> 10.590487 | F3: =D3+E3/400 -> 1.0321354 | G3: =LN(F3) -> 0.031629893
A4: 34608 | B4: Pre-2001 (OLS-rescaled) | C4: 35.735344 | D4: 1.007014 | E4: =$I$2*C4^$J$2 -> 8.9031943 | F4: =D4+E4/400 -> 1.029272 | G4: =LN(F4) -> 0.02885178
A5: 34700 | B5: Pre-2001 (OLS-rescaled) | C5: 53.910363 | D5: 1.008289 | E5: =$I$2*C5^$J$2 -> 15.545707 | F5: =D5+E5/400 -> 1.0471532 | G5: =LN(F5) -> 0.046075268
A6: 34790 | B6: Pre-2001 (OLS-rescaled) | C6: 51.209221 | D6: 1.0071529 | E6: =$I$2*C6^$J$2 -> 14.499375 | F6: =D6+E6/400 -> 1.0434013 | G6: =LN(F6) -> 0.042485875
A7: 34881 | B7: Pre-2001 (OLS-rescaled) | C7: 45.893579 | D7: 1.0060075 | E7: =$I$2*C7^$J$2 -> 12.497716 | F7: =D7+E7/400 -> 1.0372518 | G7: =LN(F7) -> 0.036574728
A8: 34973 | B8: Pre-2001 (OLS-rescaled) | C8: 44.081863 | D8: 1.0068775 | E8: =$I$2*C8^$J$2 -> 11.833673 | F8: =D8+E8/400 -> 1.0364617 | G8: =LN(F8) -> 0.035812709
A9: 35065 | B9: Pre-2001 (OLS-rescaled) | C9: 35.121762 | D9: 1.0064388 | E9: =$I$2*C9^$J$2 -> 8.6966084 | F9: =D9+E9/400 -> 1.0281803 | G9: =LN(F9) -> 0.027790517
A10: 35156 | B10: Pre-2001 (OLS-rescaled) | C10: 32.939466 | D10: 1.005995 | E10: =$I$2*C10^$J$2 -> 7.9723237 | F10: =D10+E10/400 -> 1.0259258 | G10: =LN(F10) -> 0.025595396
A11: 35247 | B11: Pre-2001 (OLS-rescaled) | C11: 26.794866 | D11: 1.0060746 | E11: =$I$2*C11^$J$2 -> 6.0261571 | F11: =D11+E11/400 -> 1.02114 | G11: =LN(F11) -> 0.020919644
A12: 35339 | B12: Pre-2001 (OLS-rescaled) | C12: 23.238726 | D12: 1.0051318 | E12: =$I$2*C12^$J$2 -> 4.9683803 | F12: =D12+E12/400 -> 1.0175527 | G12: =LN(F12) -> 0.017400459
A13: 35431 | B13: Pre-2001 (OLS-rescaled) | C13: 18.763369 | D13: 1.0048167 | E13: =$I$2*C13^$J$2 -> 3.717775 | F13: =D13+E13/400 -> 1.0141111 | G13: =LN(F13) -> 0.014012457
A14: 35521 | B14: Pre-2001 (OLS-rescaled) | C14: 18.139439 | D14: 1.0057914 | E14: =$I$2*C14^$J$2 -> 3.5511935 | F14: =D14+E14/400 -> 1.0146693 | G14: =LN(F14) -> 0.014562787
... A28: 36800 | B28: Pre-2001 (OLS-rescaled) | C28: 33.161527 | D28: 1.0062615 | E28: =$I$2*C28^$J$2 -> 8.0452648 | F28: =D28+E28/400 -> 1.0263747 | G28: =LN(F28) -> 0.026032837
A29: 36892 | B29: CDS (actual) | D29: 1.0028406 | E29: 6.28125 | F29: =D29+E29/400 -> 1.0185437 | G29: =LN(F29) -> 0.018373891
A30: 36982 | B30: CDS (actual) | D30: 1.0015389 | E30: 7.75583 | F30: =D30+E30/400 -> 1.0209285 | G30: =LN(F30) -> 0.020712469
A31: 37073 | B31: CDS (actual) | D31: 0.99884232 | E31: 11.7688 | F31: =D31+E31/400 -> 1.0282643 | G31: =LN(F31) -> 0.027872255
A32: 37165 | B32: CDS (actual) | D32: 0.9978915 | E32: 8.24583 | F32: =D32+E32/400 -> 1.0185061 | G32: =LN(F32) -> 0.018336921
A33: 37257 | B33: CDS (actual) | D33: 1.0005734 | E33: 7.18 | F33: =D33+E33/400 -> 1.0185234 | G33: =LN(F33) -> 0.018353884
A34: 37347 | B34: CDS (actual) | D34: 1.0009201 | E34: 21.9375 | F34: =D34+E34/400 -> 1.0557639 | G34: =LN(F34) -> 0.054264545
A35: 37438 | B35: CDS (actual) | D35: 1.0014751 | E35: 37.3336 | F35: =D35+E35/400 -> 1.0948091 | G35: =LN(F35) -> 0.090580031
A36: 37530 | B36: CDS (actual) | D36: 0.99924927 | E36: 21.47 | F36: =D36+E36/400 -> 1.0529243 | G36: =LN(F36) -> 0.051571309
A37: 37622 | B37: CDS (actual) | D37: 0.99675105 | E37: 13.6958 | F37: =D37+E37/400 -> 1.0309906 | G37: =LN(F37) -> 0.030520043
A38: 37712 | B38: CDS (actual) | D38: 0.99490658 | E38: 8.89917 | F38: =D38+E38/400 -> 1.0171545 | G38: =LN(F38) -> 0.017009027
A39: 37803 | B39: CDS (actual) | D39: 0.99755849 | E39: 7.63 | F39: =D39+E39/400 -> 1.0166335 | G39: =LN(F39) -> 0.016496665
A40: 37895 | B40: CDS (actual) | D40: 0.99638266 | E40: 4.03844 | F40: =D40+E40/400 -> 1.0064788 | G40: =LN(F40) -> 0.0064578622
... A130: 46113 | B130: CDS (actual) | D130: 1.0013931 | E130: 1.26828 | F130: =D130+E130/400 -> 1.0045638 | G130: =LN(F130) -> 0.0045534243

Sheet Brazil_interest
A1: Date | B1: Source | C1: Ours_raw (pre-2001 only) | D1: Rus_gross_q | E1: Spread_%_annual (reconciled) | F1: R_gross_q | G1: R_hat (ln level) | H1: statadata_Rhat (original paper, 1994-2001) | I1: irs_data_Rhat (ln_R level, 1994-2012) | J1: R_hat_final (paper formulation) | L1: R2 (log-log) | M1: OLS a | N1: OLS b | O1: R2
A2: 34425 | B2: Pre-2001 (OLS-rescaled) | C2: 48.499784 | D2: 1.0040327 | E2: =$I$2*C2^$J$2 -> 0.21734085 | F2: =D2+E2/400 -> 1.0045761 | G2: =LN(F2) -> 0.0045656592 | I2: 0.1310676 | J2: =$M$2+$N$2*I2 -> 0.13029652 | L2: 0.95415963 | M2: 0.014315513 | N2: 0.88489457 | O2: 0.7479273
A3: 34516 | B3: Pre-2001 (OLS-rescaled) | C3: 40.616217 | D3: 1.0056592 | E3: =$I$2*C3^$J$2 -> 0.21237494 | F3: =D3+E3/400 -> 1.0061902 | G3: =LN(F3) -> 0.0061710747 | H3: 0.1368833 | I3: 0.11891972 | J3: =H3 -> 0.1368833
A4: 34608 | B4: Pre-2001 (OLS-rescaled) | C4: 35.735344 | D4: 1.007014 | E4: =$I$2*C4^$J$2 -> 0.20886159 | F4: =D4+E4/400 -> 1.0075362 | G4: =LN(F4) -> 0.0075079377 | H4: 0.1019278 | I4: 0.11743811 | J4: =H4 -> 0.1019278
A5: 34700 | B5: Pre-2001 (OLS-rescaled) | C5: 53.910363 | D5: 1.008289 | E5: =$I$2*C5^$J$2 -> 0.22035667 | F5: =D5+E5/400 -> 1.0088398 | G5: =LN(F5) -> 0.0088010065 | H5: 0.1291245 | I5: 0.15789981 | J5: =H5 -> 0.1291245
A6: 34790 | B6: Pre-2001 (OLS-rescaled) | C6: 51.209221 | D6: 1.0071529 | E6: =$I$2*C6^$J$2 -> 0.21888573 | F6: =D6+E6/400 -> 1.0077001 | G6: =LN(F6) -> 0.0076706011 | H6: 0.1741788 | I6: 0.14904512 | J6: =H6 -> 0.1741788
A7: 34881 | B7: Pre-2001 (OLS-rescaled) | C7: 45.893579 | D7: 1.0060075 | E7: =$I$2*C7^$J$2 -> 0.2157823 | F7: =D7+E7/400 -> 1.006547 | G7: =LN(F7) -> 0.0065256396 | H7: 0.140343 | I7: 0.13639871 | J7: =H7 -> 0.140343
A8: 34973 | B8: Pre-2001 (OLS-rescaled) | C8: 44.081863 | D8: 1.0068775 | E8: =$I$2*C8^$J$2 -> 0.21465286 | F8: =D8+E8/400 -> 1.0074142 | G8: =LN(F8) -> 0.007386808 | H8: 0.1308381 | I8: 0.13180942 | J8: =H8 -> 0.1308381
A9: 35065 | B9: Pre-2001 (OLS-rescaled) | C9: 35.121762 | D9: 1.0064388 | E9: =$I$2*C9^$J$2 -> 0.2083908 | F9: =D9+E9/400 -> 1.0069597 | G9: =LN(F9) -> 0.0069356247 | H9: 0.1193185 | I9: 0.1108963 | J9: =H9 -> 0.1193185
A10: 35156 | B10: Pre-2001 (OLS-rescaled) | C10: 32.939466 | D10: 1.005995 | E10: =$I$2*C10^$J$2 -> 0.20665624 | F10: =D10+E10/400 -> 1.0065116 | G10: =LN(F10) -> 0.0064904931 | H10: 0.1139008 | I10: 0.10748797 | J10: =H10 -> 0.1139008
A11: 35247 | B11: Pre-2001 (OLS-rescaled) | C11: 26.794866 | D11: 1.0060746 | E11: =$I$2*C11^$J$2 -> 0.20117105 | F11: =D11+E11/400 -> 1.0065775 | G11: =LN(F11) -> 0.0065559908 | H11: 0.1050886 | I11: 0.094170012 | J11: =H11 -> 0.1050886
A12: 35339 | B12: Pre-2001 (OLS-rescaled) | C12: 23.238726 | D12: 1.0051318 | E12: =$I$2*C12^$J$2 -> 0.19747314 | F12: =D12+E12/400 -> 1.0056255 | G12: =LN(F12) -> 0.0056096977 | H12: 0.0848354 | I12: 0.086260565 | J12: =H12 -> 0.0848354
A13: 35431 | B13: Pre-2001 (OLS-rescaled) | C13: 18.763369 | D13: 1.0048167 | E13: =$I$2*C13^$J$2 -> 0.19204513 | F13: =D13+E13/400 -> 1.0052968 | G13: =LN(F13) -> 0.0052827882 | H13: 0.0838366 | I13: 0.07797087 | J13: =H13 -> 0.0838366
A14: 35521 | B14: Pre-2001 (OLS-rescaled) | C14: 18.139439 | D14: 1.0057914 | E14: =$I$2*C14^$J$2 -> 0.19120077 | F14: =D14+E14/400 -> 1.0062694 | G14: =LN(F14) -> 0.0062497884 | H14: 0.0824513 | I14: 0.073762136 | J14: =H14 -> 0.0824513
... A28: 36800 | B28: Pre-2001 (OLS-rescaled) | C28: 33.161527 | D28: 1.0062615 | E28: =$I$2*C28^$J$2 -> 0.20683723 | F28: =D28+E28/400 -> 1.0067786 | G28: =LN(F28) -> 0.0067557105 | H28: 0.1121441 | I28: 0.10955668 | J28: =H28 -> 0.1121441
A29: 36892 | B29: CDS (actual) | D29: 1.0028406 | E29: 6.28125 | F29: =D29+E29/400 -> 1.0185437 | G29: =LN(F29) -> 0.018373891 | H29: 0.1126679 | I29: 0.091526294 | J29: =H29 -> 0.1126679
A30: 36982 | B30: CDS (actual) | D30: 1.0015389 | E30: 7.75583 | F30: =D30+E30/400 -> 1.0209285 | G30: =LN(F30) -> 0.020712469 | H30: 0.1001101 | I30: 0.093222137 | J30: =H30 -> 0.1001101
A31: 37073 | B31: CDS (actual) | D31: 0.99884232 | E31: 11.7688 | F31: =D31+E31/400 -> 1.0282643 | G31: =LN(F31) -> 0.027872255 | H31: 0.1009832 | I31: 0.098469707 | J31: =H31 -> 0.1009832
A32: 37165 | B32: CDS (actual) | D32: 0.9978915 | E32: 8.24583 | F32: =D32+E32/400 -> 1.0185061 | G32: =LN(F32) -> 0.018336921 | H32: 0.1111783 | I32: 0.097034562 | J32: =H32 -> 0.1111783
A33: 37257 | B33: CDS (actual) | D33: 1.0005734 | E33: 7.18 | F33: =D33+E33/400 -> 1.0185234 | G33: =LN(F33) -> 0.018353884 | I33: 0.078799869 | J33: =$M$2+$N$2*I33 -> 0.084045089
A34: 37347 | B34: CDS (actual) | D34: 1.0009201 | E34: 21.9375 | F34: =D34+E34/400 -> 1.0557639 | G34: =LN(F34) -> 0.054264545 | I34: 0.10134065 | J34: =$M$2+$N$2*I34 -> 0.10399131
A35: 37438 | B35: CDS (actual) | D35: 1.0014751 | E35: 37.3336 | F35: =D35+E35/400 -> 1.0948091 | G35: =LN(F35) -> 0.090580031 | I35: 0.19136959 | J35: =$M$2+$N$2*I35 -> 0.18365743
A36: 37530 | B36: CDS (actual) | D36: 0.99924927 | E36: 21.47 | F36: =D36+E36/400 -> 1.0529243 | G36: =LN(F36) -> 0.051571309 | I36: 0.17342492 | J36: =$M$2+$N$2*I36 -> 0.16777828
A37: 37622 | B37: CDS (actual) | D37: 0.99675105 | E37: 13.6958 | F37: =D37+E37/400 -> 1.0309906 | G37: =LN(F37) -> 0.030520043 | I37: 0.11853277 | J37: =$M$2+$N$2*I37 -> 0.11920451
A38: 37712 | B38: CDS (actual) | D38: 0.99490658 | E38: 8.89917 | F38: =D38+E38/400 -> 1.0171545 | G38: =LN(F38) -> 0.017009027 | I38: 0.070798259 | J38: =$M$2+$N$2*I38 -> 0.076964508
A39: 37803 | B39: CDS (actual) | D39: 0.99755849 | E39: 7.63 | F39: =D39+E39/400 -> 1.0166335 | G39: =LN(F39) -> 0.016496665 | I39: 0.064769777 | J39: =$M$2+$N$2*I39 -> 0.071629937
A40: 37895 | B40: CDS (actual) | D40: 0.99638266 | E40: 4.03844 | F40: =D40+E40/400 -> 1.0064788 | G40: =LN(F40) -> 0.0064578622 | I40: 0.044893334 | J40: =$M$2+$N$2*I40 -> 0.05404138
A41: 37987 | B41: CDS (actual) | D41: 0.99731737 | E41: 5.76607 | F41: =D41+E41/400 -> 1.0117325 | G41: =LN(F41) -> 0.011664249 | I41: 0.040938493 | J41: =$M$2+$N$2*I41 -> 0.050541763
A42: 38078 | B42: CDS (actual) | D42: 0.99889003 | E42: 7.10853 | F42: =D42+E42/400 -> 1.0166614 | G42: =LN(F42) -> 0.016524081 | I42: 0.056669464 | J42: =$M$2+$N$2*I42 -> 0.064462014
A43: 38169 | B43: CDS (actual) | D43: 0.99639577 | E43: 4.36109 | F43: =D43+E43/400 -> 1.0072985 | G43: =LN(F43) -> 0.007271988 | I43: 0.044463353 | J43: =$M$2+$N$2*I43 -> 0.053660893
A44: 38261 | B44: CDS (actual) | D44: 0.99926183 | E44: 3.06096 | F44: =D44+E44/400 -> 1.0069142 | G44: =LN(F44) -> 0.0068904315 | I44: 0.036916227 | J44: =$M$2+$N$2*I44 -> 0.046982482
... A76: 41183 | B76: CDS (actual) | D76: 0.99534824 | E76: 1.07704 | F76: =D76+E76/400 -> 0.99804084 | G76: =LN(F76) -> -0.0019610827 | I76: 0.00017162937 | J76: =$M$2+$N$2*I76 -> 0.014467387
A77: 41275 | B77: CDS (actual) | D77: 0.99586154 | E77: 1.3743 | F77: =D77+E77/400 -> 0.99929729 | G77: =LN(F77) -> -0.00070295866 | J77: =$M$2+$N$2*G77 -> 0.013693469
A78: 41365 | B78: CDS (actual) | D78: 0.99635282 | E78: 1.8604 | F78: =D78+E78/400 -> 1.0010038 | G78: =LN(F78) -> 0.0010033204 | J78: =$M$2+$N$2*G78 -> 0.015203346
A79: 41456 | B79: CDS (actual) | D79: 0.99579732 | E79: 1.77132 | F79: =D79+E79/400 -> 1.0002256 | G79: =LN(F79) -> 0.0002255925 | J79: =$M$2+$N$2*G79 -> 0.014515139
A80: 41548 | B80: CDS (actual) | D80: 0.99745441 | E80: 1.93 | F80: =D80+E80/400 -> 1.0022794 | G80: =LN(F80) -> 0.0022768158 | J80: =$M$2+$N$2*G80 -> 0.016330255
A81: 41640 | B81: CDS (actual) | D81: 0.99637624 | E81: 1.71 | F81: =D81+E81/400 -> 1.0006512 | G81: =LN(F81) -> 0.00065102487 | J81: =$M$2+$N$2*G81 -> 0.014891601
A82: 41730 | B82: CDS (actual) | D82: 0.99610617 | E82: 1.43695 | F82: =D82+E82/400 -> 0.99969854 | G82: =LN(F82) -> -0.00030150497 | J82: =$M$2+$N$2*G82 -> 0.014048713
A83: 41821 | B83: CDS (actual) | D83: 0.99496748 | E83: 1.76197 | F83: =D83+E83/400 -> 0.99937241 | G83: =LN(F83) -> -0.00062779133 | J83: =$M$2+$N$2*G83 -> 0.013759984
A84: 41913 | B84: CDS (actual) | D84: 0.99590667 | E84: 1.97547 | F84: =D84+E84/400 -> 1.0008453 | G84: =LN(F84) -> 0.00084498291 | J84: =$M$2+$N$2*G84 -> 0.015063234
A85: 42005 | B85: CDS (actual) | D85: 0.99843948 | E85: 2.8165 | F85: =D85+E85/400 -> 1.0054807 | G85: =LN(F85) -> 0.0054657657 | J85: =$M$2+$N$2*G85 -> 0.019152139
A86: 42095 | B86: CDS (actual) | D86: 1.0000982 | E86: 2.61 | F86: =D86+E86/400 -> 1.0066232 | G86: =LN(F86) -> 0.006601373 | J86: =$M$2+$N$2*G86 -> 0.020157032
A87: 42186 | B87: CDS (actual) | D87: 0.9995917 | E87: 4.77 | F87: =D87+E87/400 -> 1.0115167 | G87: =LN(F87) -> 0.011450892 | J87: =$M$2+$N$2*G87 -> 0.024448345
A88: 42278 | B88: CDS (actual) | D88: 1.000543 | E88: 5 | F88: =D88+E88/400 -> 1.013043 | G88: =LN(F88) -> 0.012958671 | J88: =$M$2+$N$2*G88 -> 0.025782571
... A130: 46113 | B130: CDS (actual) | D130: 1.0013931 | E130: 1.26828 | F130: =D130+E130/400 -> 1.0045638 | G130: =LN(F130) -> 0.0045534243 | J130: =$M$2+$N$2*G130 -> 0.018344813

Sheet PIB
A1: Data | B1: 22109 - PIB trimestral - Dados dessazonalizados - Produto Interno Bruto a preços de mercado - Índice | E1: LOG(PIB) | F1: LINEAR TREND | G1: logdysa | H1: logdysa_original
A2: 1° Trim.1996 | B2: 99.41 | C2: =(B2/#REF!-1)*100 -> #REF! | D2: {=TRANSPOSE('crescimento PIB'!C4:$DS$4)} -> 2.5 | E2: =LN(B2) -> 4.5992527 | F2: {=TREND($E$2:$E$122)} -> 4.6539879 | G2: =E2-F2 -> -0.054735166 | H2: -0.0112256
A3: 2° Trim.1996 | B3: 100.6 | C3: =(B3/#REF!-1)*100 -> #REF! | D3: 2.1 | E3: =LN(B3) -> 4.6111523 | F3: 4.659526 | G3: =E3-F3 -> -0.048373709 | H3: -0.0017872
A4: 3° Trim.1996 | B4: 104.31 | C4: =(B4/#REF!-1)*100 -> #REF! | D4: 2.3 | E4: =LN(B4) -> 4.6473672 | F4: 4.6650641 | G4: =E4-F4 -> -0.017696821 | H4: 0.0266512
A5: 4° Trim.1996 | B5: 103.32 | D5: 2.2 | E5: =LN(B5) -> 4.637831 | F5: 4.6706021 | G5: =E5-F5 -> -0.032771176 | H5: 0.0190896
A6: 1° Trim.1997 | B6: 104.43 | C6: =(B6/B2-1)*100 -> 5.0497938 | D6: 3.2 | E6: =LN(B6) -> 4.648517 | F6: 4.6761402 | G6: =E6-F6 -> -0.027623242 | H6: 0.012528
A7: 2° Trim.1997 | B7: 104.93 | C7: =(B7/B3-1)*100 -> 4.304175 | D7: 4 | E7: =LN(B7) -> 4.6532935 | F7: 4.6816783 | G7: =E7-F7 -> -0.02838486 | H7: 0.0199665
A8: 3° Trim.1997 | B8: 106.27 | C8: =(B8/B4-1)*100 -> 1.8790145 | D8: 3 | E8: =LN(B8) -> 4.665983 | F8: 4.6872164 | G8: =E8-F8 -> -0.021233384 | H8: 0.0244049
A9: 4° Trim.1997 | B9: 107.16 | C9: =(B9/B5-1)*100 -> 3.7166086 | D9: 3.4 | E9: =LN(B9) -> 4.674323 | F9: 4.6927545 | G9: =E9-F9 -> -0.018431453 | H9: 0.0188433
A10: 1° Trim.1998 | B10: 105.04 | C10: =(B10/B6-1)*100 -> 0.58412334 | D10: 2.8 | E10: =LN(B10) -> 4.6543412 | F10: 4.6982926 | G10: =E10-F10 -> -0.043951356 | H10: -0.0017183
A11: 2° Trim.1998 | B11: 106.85 | C11: =(B11/B7-1)*100 -> 1.8297913 | D11: 2 | E11: =LN(B11) -> 4.671426 | F11: 4.7038307 | G11: =E11-F11 -> -0.032404693 | H11: 0.0117201
A12: 3° Trim.1998 | B12: 106.81 | C12: =(B12/B8-1)*100 -> 0.50813964 | D12: 1.6 | E12: =LN(B12) -> 4.6710516 | F12: 4.7093688 | G12: =E12-F12 -> -0.038317208 | H12: 0.0041585
A13: 4° Trim.1998 | B13: 105.59 | C13: =(B13/B9-1)*100 -> -1.4650989 | D13: 0.3 | E13: =LN(B13) -> 4.6595637 | F13: 4.7149069 | G13: =E13-F13 -> -0.055343181 | H13: -0.021403
A14: 1° Trim.1999 | B14: 105.78 | C14: =(B14/B10-1)*100 -> 0.70449353 | D14: 0.3 | E14: =LN(B14) -> 4.6613615 | F14: 4.7204449 | G14: =E14-F14 -> -0.059083474 | H14: -0.0189646
A15: 2° Trim.1999 | B15: 106.34 | C15: =(B15/B11-1)*100 -> -0.47730463 | D15: -0.2 | E15: =LN(B15) -> 4.6666415 | F15: 4.725983 | G15: =E15-F15 -> -0.05934152 | H15: -0.0175262
A16: 3° Trim.1999 | B16: 106.34 | C16: =(B16/B12-1)*100 -> -0.4400337 | D16: -0.4 | E16: =LN(B16) -> 4.6666415 | F16: 4.7315211 | G16: =E16-F16 -> -0.064879608 | H16: -0.0200878
A17: 4° Trim.1999 | B17: 107.85 | C17: =(B17/B13-1)*100 -> 2.1403542 | D17: 0.5 | E17: =LN(B17) -> 4.6807414 | F17: 4.7370592 | G17: =E17-F17 -> -0.056317832 | H17: -0.0076494
... A25: 4° Trim.2001 | B25: 112.16 | C25: =(B25/B21-1)*100 -> -0.91872792 | D25: 1.4 | E25: =LN(B25) -> 4.7199264 | F25: 4.7813639 | G25: =E25-F25 -> -0.061437489 | H25: -0.021142
A26: 1° Trim.2002 | B26: 114.94 | C26: =(B26/B22-1)*100 -> 1.1706716 | D26: 0.7 | E26: =LN(B26) -> 4.7444103 | F26: 4.786902 | G26: =E26-F26 -> -0.042491747
A27: 2° Trim.2002 | B27: 115.19 | C27: =(B27/B23-1)*100 -> 1.8749447 | D27: 0.7 | E27: =LN(B27) -> 4.7465829 | F27: 4.7924401 | G27: =E27-F27 -> -0.04585715
A28: 3° Trim.2002 | B28: 116.8 | C28: =(B28/B24-1)*100 -> 3.8499155 | D28: 1.6 | E28: =LN(B28) -> 4.7604631 | F28: 4.7979782 | G28: =E28-F28 -> -0.037515107
A29: 4° Trim.2002 | B29: 118 | C29: =(B29/B25-1)*100 -> 5.2068474 | D29: 3.1 | E29: =LN(B29) -> 4.7706846 | F29: 4.8035163 | G29: =E29-F29 -> -0.032831641
A30: 1° Trim.2003 | B30: 117.47 | C30: =(B30/B26-1)*100 -> 2.2011484 | D30: 3.6 | E30: =LN(B30) -> 4.766183 | F30: 4.8090544 | G30: =E30-F30 -> -0.042871372
A31: 2° Trim.2003 | B31: 116.48 | C31: =(B31/B27-1)*100 -> 1.1198889 | D31: 3.2 | E31: =LN(B31) -> 4.7577196 | F31: 4.8145924 | G31: =E31-F31 -> -0.056872858
A32: 3° Trim.2003 | B32: 117.58 | C32: =(B32/B28-1)*100 -> 0.66780822 | D32: 2.3 | E32: =LN(B32) -> 4.767119 | F32: 4.8201305 | G32: =E32-F32 -> -0.053011578
A33: 4° Trim.2003 | B33: 118.81 | C33: =(B33/B29-1)*100 -> 0.68644068 | D33: 1.1 | E33: =LN(B33) -> 4.7775256 | F33: 4.8256686 | G33: =E33-F33 -> -0.048143041
A34: 1° Trim.2004 | B34: 120.44 | C34: =(B34/B30-1)*100 -> 2.5283051 | D34: 1.4 | E34: =LN(B34) -> 4.7911517 | F34: 4.8312067 | G34: =E34-F34 -> -0.040055004
A35: 2° Trim.2004 | B35: 123.76 | C35: =(B35/B31-1)*100 -> 6.25 | D35: 2.8 | E35: =LN(B35) -> 4.8183442 | F35: 4.8367448 | G35: =E35-F35 -> -0.01840059
A36: 3° Trim.2004 | B36: 125.34 | C36: =(B36/B32-1)*100 -> 6.5997619 | D36: 4.3 | E36: =LN(B36) -> 4.83103 | F36: 4.8422829 | G36: =E36-F36 -> -0.01125284
A37: 4° Trim.2004 | B37: 126.3 | C37: =(B37/B33-1)*100 -> 6.3041831 | D37: 5.8 | E37: =LN(B37) -> 4.83866 | F37: 4.847821 | G37: =E37-F37 -> -0.0091609437
... A122: 1° Trim.2026 | B122: 197.34 | C122: =(B122/B118-1)*100 -> 1.8056129 | D122: 2 | E122: =LN(B122) -> 5.2849281 | F122: 5.3185585 | G122: =E122-F122 -> -0.033630359
A123: Fonte | B123: IBGE | E123: =LN(B123) -> #VALUE! | G123: =E123-F123 -> #VALUE!

Sheet crescimento PIB
A1: PIB a preços de mercado - Taxa acumulada em 4 trimestres
C2: 1º trimestre 1996 | D2: 2º trimestre 1996 | E2: 3º trimestre 1996 | F2: 4º trimestre 1996 | G2: 1º trimestre 1997 | H2: 2º trimestre 1997 | I2: 3º trimestre 1997 | J2: 4º trimestre 1997 | K2: 1º trimestre 1998 | L2: 2º trimestre 1998 | M2: 3º trimestre 1998 | N2: 4º trimestre 1998 | O2: 1º trimestre 1999 | P2: 2º trimestre 1999 | Q2: 3º trimestre 1999 | R2: 4º trimestre 1999 | S2: 1º trimestre 2000 | T2: 2º trimestre 2000 | U2: 3º trimestre 2000 | V2: 4º trimestre 2000 | W2: 1º trimestre 2001 | X2: 2º trimestre 2001 | Y2: 3º trimestre 2001 | Z2: 4º trimestre 2001 | AA2: 1º trimestre 2002 | AB2: 2º trimestre 2002 | AC2: 3º trimestre 2002 | AD2: 4º trimestre 2002 | AE2: 1º trimestre 2003 | AF2: 2º trimestre 2003 | AG2: 3º trimestre 2003 | AH2: 4º trimestre 2003 | AI2: 1º trimestre 2004 | AJ2: 2º trimestre 2004 | AK2: 3º trimestre 2004 | AL2: 4º trimestre 2004 | AM2: 1º trimestre 2005 | AN2: 2º trimestre 2005 | AO2: 3º trimestre 2005 | AP2: 4º trimestre 2005 | AQ2: 1º trimestre 2006 | AR2: 2º trimestre 2006 | AS2: 3º trimestre 2006 | AT2: 4º trimestre 2006 | AU2: 1º trimestre 2007 | AV2: 2º trimestre 2007 | AW2: 3º trimestre 2007 | AX2: 4º trimestre 2007 | AY2: 1º trimestre 2008 | AZ2: 2º trimestre 2008 | BA2: 3º trimestre 2008 | BB2: 4º trimestre 2008 | BC2: 1º trimestre 2009 | BD2: 2º trimestre 2009 | BE2: 3º trimestre 2009 | BF2: 4º trimestre 2009 | BG2: 1º trimestre 2010 | BH2: 2º trimestre 2010 | BI2: 3º trimestre 2010 | BJ2: 4º trimestre 2010 | BK2: 1º trimestre 2011 | BL2: 2º trimestre 2011 | BM2: 3º trimestre 2011 | BN2: 4º trimestre 2011 | BO2: 1º trimestre 2012 | BP2: 2º trimestre 2012 | BQ2: 3º trimestre 2012 | BR2: 4º trimestre 2012 | BS2: 1º trimestre 2013 | BT2: 2º trimestre 2013 | BU2: 3º trimestre 2013 | BV2: 4º trimestre 2013 | BW2: 1º trimestre 2014 | BX2: 2º trimestre 2014 | BY2: 3º trimestre 2014 | BZ2: 4º trimestre 2014 | CA2: 1º trimestre 2015 | CB2: 2º trimestre 2015 | CC2: 3º trimestre 2015 | CD2: 4º trimestre 2015 | CE2: 1º trimestre 2016 | CF2: 2º trimestre 2016 | CG2: 3º trimestre 2016 | CH2: 4º trimestre 2016 | CI2: 1º trimestre 2017 | CJ2: 2º trimestre 2017 | CK2: 3º trimestre 2017 | CL2: 4º trimestre 2017 | CM2: 1º trimestre 2018 | CN2: 2º trimestre 2018 | CO2: 3º trimestre 2018 | CP2: 4º trimestre 2018 | CQ2: 1º trimestre 2019 | CR2: 2º trimestre 2019 | CS2: 3º trimestre 2019 | CT2: 4º trimestre 2019 | CU2: 1º trimestre 2020 | CV2: 2º trimestre 2020 | CW2: 3º trimestre 2020 | CX2: 4º trimestre 2020 | CY2: 1º trimestre 2021 | CZ2: 2º trimestre 2021 | DA2: 3º trimestre 2021 | DB2: 4º trimestre 2021 | DC2: 1º trimestre 2022 | DD2: 2º trimestre 2022 | DE2: 3º trimestre 2022 | DF2: 4º trimestre 2022 | DG2: 1º trimestre 2023 | DH2: 2º trimestre 2023 | DI2: 3º trimestre 2023 | DJ2: 4º trimestre 2023 | DK2: 1º trimestre 2024 | DL2: 2º trimestre 2024 | DM2: 3º trimestre 2024 | DN2: 4º trimestre 2024 | DO2: 1º trimestre 2025 | DP2: 2º trimestre 2025 | DQ2: 3º trimestre 2025 | DR2: 4º trimestre 2025 | DS2: 1º trimestre 2026
A4: Brasil | C4: 2.5 | D4: 2.1 | E4: 2.3 | F4: 2.2 | G4: 3.2 | H4: 4 | I4: 3 | J4: 3.4 | K4: 2.8 | L4: 2 | M4: 1.6 | N4: 0.3 | O4: 0.3 | P4: -0.2 | Q4: -0.4 | R4: 0.5 | S4: 1.3 | T4: 2.4 | U4: 3.8 | V4: 4.4 | W4: 4.2 | X4: 3.7 | Y4: 2.7 | Z4: 1.4 | AA4: 0.7 | AB4: 0.7 | AC4: 1.6 | AD4: 3.1 | AE4: 3.6 | AF4: 3.2 | AG4: 2.3 | AH4: 1.1 | AI4: 1.4 | AJ4: 2.8 | AK4: 4.3 | AL4: 5.8 | AM4: 5.8 | AN4: 5.4 | AO4: 4.2 | AP4: 3.2 | AQ4: 3.2 | AR4: 2.7 | AS4: 3.3 | AT4: 4 | AU4: 4.2 | AV4: 5.3 | AW4: 5.6 | AX4: 6.1 | AY4: 6.3 | AZ4: 6.3 | BA4: 6.5 | BB4: 5.1 | BC4: 3 | BD4: 0.8 | BE4: -1.2 | BF4: -0.1 | BG4: 2.6 | BH4: 5.3 | BI4: 7.5 | BJ4: 7.5 | BK4: 6.6 | BL4: 5.6 | BM4: 4.8 | BN4: 4 | BO4: 3.1 | BP4: 2.2 | BQ4: 1.9 | BR4: 1.9 | BS4: 2.2 | BT4: 2.9 | BU4: 3 | BV4: 3 | BW4: 3.2 | BX4: 2.1 | BY4: 1.2 | BZ4: 0.5 | CA4: -0.7 | CB4: -1.3 | CC4: -2.2 | CD4: -3.5 | CE4: -4.4 | CF4: -4.5 | CG4: -4.1 | CH4: -3.3 | CI4: -1.9 | CJ4: -0.9 | CK4: 0.1 | CL4: 1.3 | CM4: 1.7 | CN4: 1.9 | CO4: 2 | CP4: 1.8 | CQ4: 1.5 | CR4: 1.4 | CS4: 1.2 | CT4: 1.2 | CU4: 1.1 | CV4: -1.7 | CW4: -2.8 | CX4: -3.3 | CY4: -2.9 | CZ4: 2.4 | DA4: 4.3 | DB4: 4.8 | DC4: 4.7 | DD4: 2.7 | DE4: 2.7 | DF4: 3 | DG4: 3.8 | DH4: 3.8 | DI4: 3.3 | DJ4: 3.2 | DK4: 2.8 | DL4: 2.7 | DM4: 3.1 | DN4: 3.4 | DO4: 3.6 | DP4: 3.3 | DQ4: 2.7 | DR4: 2.3 | DS4: 2
A5: Fonte: "IBGE - Contas Nacionais Trimestrais"

Sheet INV
A1: Data | B1: 22113 - PIB trimestral - Dados dessazonalizados - FBCF - Índice | E1: LOG(INV) | F1: LINEAR TREND | G1: logdysa | H1: logdysa_original
A2: 1° Trim.1996 | B2: 96.84 | E2: =LN(B2) -> 4.5730601 | F2: {=TREND($E$2:$E$122)} -> 4.6247716 | G2: =E2-F2 -> -0.051711441 | H2: -0.0894128 | I2: {=TREND(E2:E25)} -> 4.6542554 | J2: =E2-I2 -> -0.081195279
A3: 2° Trim.1996 | B3: 98.71 | E3: =LN(B3) -> 4.5921863 | F3: 4.629929 | G3: =E3-F3 -> -0.037742761 | H3: -0.0609161 | I3: 4.6542668 | J3: =E3-I3 -> -0.062080587
A4: 3° Trim.1996 | B4: 102.41 | E4: =LN(B4) -> 4.6289844 | F4: 4.6350865 | G4: =E4-F4 -> -0.0061021024 | H4: -0.0124194 | I4: 4.6542783 | J4: =E4-I4 -> -0.025293916
A5: 4° Trim.1996 | B5: 106.78 | E5: =LN(B5) -> 4.6707706 | F5: 4.6402439 | G5: =E5-F5 -> 0.03052673 | H5: 0.0030773 | I5: 4.6542897 | J5: =E5-I5 -> 0.016480928
A6: 1° Trim.1997 | B6: 107.68 | E6: =LN(B6) -> 4.6791639 | F6: 4.6454014 | G6: =E6-F6 -> 0.033762506 | H6: 0.003574 | I6: 4.6543011 | J6: =E6-I6 -> 0.024862716
A7: 2° Trim.1997 | B7: 109.2 | E7: =LN(B7) -> 4.6931811 | F7: 4.6505588 | G7: =E7-F7 -> 0.042622257 | H7: 0.0250707 | I7: 4.6543126 | J7: =E7-I7 -> 0.038868479
A8: 3° Trim.1997 | B8: 111.34 | E8: =LN(B8) -> 4.7125886 | F8: 4.6557163 | G8: =E8-F8 -> 0.056872329 | H8: 0.0375674 | I8: 4.654324 | J8: =E8-I8 -> 0.058264564
A9: 4° Trim.1997 | B9: 110.61 | E9: =LN(B9) -> 4.7060105 | F9: 4.6608737 | G9: =E9-F9 -> 0.045136801 | H9: -0.0069359 | I9: 4.6543355 | J9: =E9-I9 -> 0.051675047
A10: 1° Trim.1998 | B10: 111.21 | E10: =LN(B10) -> 4.7114203 | F10: 4.6660311 | G10: =E10-F10 -> 0.045389159 | H10: 0.0025609 | I10: 4.6543469 | J10: =E10-I10 -> 0.057073417
A11: 2° Trim.1998 | B11: 111.62 | E11: =LN(B11) -> 4.7151002 | F11: 4.6711886 | G11: =E11-F11 -> 0.043911652 | H11: 0.0050576 | I11: 4.6543583 | J11: =E11-I11 -> 0.060741922
A12: 3° Trim.1998 | B12: 110.18 | E12: =LN(B12) -> 4.7021154 | F12: 4.676346 | G12: =E12-F12 -> 0.025769352 | H12: 0.0045543 | I12: 4.6543698 | J12: =E12-I12 -> 0.047745634
A13: 4° Trim.1998 | B13: 105.22 | E13: =LN(B13) -> 4.6560534 | F13: 4.6815035 | G13: =E13-F13 -> -0.025450091 | H13: -0.026949 | I13: 4.6543812 | J13: =E13-I13 -> 0.0016722037
A14: 1° Trim.1999 | B14: 101.47 | E14: =LN(B14) -> 4.6197632 | F14: 4.6866609 | G14: =E14-F14 -> -0.066897745 | H14: -0.0594523 | I14: 4.6543926 | J14: =E14-I14 -> -0.034629439
... A25: 4° Trim.2001 | B25: 100.06 | E25: =LN(B25) -> 4.60577 | F25: 4.7433928 | G25: =E25-F25 -> -0.13762284 | H25: -0.0219886 | I25: 4.6545184 | J25: =E25-I25 -> -0.048748403
A26: 1° Trim.2002 | B26: 101.27 | E26: =LN(B26) -> 4.6177902 | F26: 4.7485503 | G26: =E26-F26 -> -0.13076008
A27: 2° Trim.2002 | B27: 103.63 | E27: =LN(B27) -> 4.6408269 | F27: 4.7537077 | G27: =E27-F27 -> -0.11288088
A28: 3° Trim.2002 | B28: 105.25 | E28: =LN(B28) -> 4.6563385 | F28: 4.7588652 | G28: =E28-F28 -> -0.10252671
A29: 4° Trim.2002 | B29: 107.49 | E29: =LN(B29) -> 4.6773978 | F29: 4.7640226 | G29: =E29-F29 -> -0.086624814
A30: 1° Trim.2003 | B30: 104.31 | E30: =LN(B30) -> 4.6473672 | F30: 4.7691801 | G30: =E30-F30 -> -0.12181285
A31: 2° Trim.2003 | B31: 97.05 | E31: =LN(B31) -> 4.5752263 | F31: 4.7743375 | G31: =E31-F31 -> -0.19911122
A32: 3° Trim.2003 | B32: 97.7 | E32: =LN(B32) -> 4.5819016 | F32: 4.779495 | G32: =E32-F32 -> -0.19759342
A33: 4° Trim.2003 | B33: 102.1 | E33: =LN(B33) -> 4.6259527 | F33: 4.7846524 | G33: =E33-F33 -> -0.1586997
A34: 1° Trim.2004 | B34: 105.37 | E34: =LN(B34) -> 4.657478 | F34: 4.7898099 | G34: =E34-F34 -> -0.1323319
A35: 2° Trim.2004 | B35: 108.97 | E35: =LN(B35) -> 4.6910726 | F35: 4.7949673 | G35: =E35-F35 -> -0.1038947
A36: 3° Trim.2004 | B36: 111.18 | E36: =LN(B36) -> 4.7111505 | F36: 4.8001248 | G36: =E36-F36 -> -0.088974251
A37: 4° Trim.2004 | B37: 109.33 | E37: =LN(B37) -> 4.6943708 | F37: 4.8052822 | G37: =E37-F37 -> -0.11091138
... A122: 1° Trim.2026 | B122: 181.67 | E122: =LN(B122) -> 5.2021919 | F122: 5.2436652 | G122: =E122-F122 -> -0.041473323
A123: Fonte | B123: IBGE | E123: =LN(B123) -> #VALUE! | G123: =E123-F123 -> #VALUE!

Sheet balança comercial_bens
A1: Data | B1: 23087 - Balança comercial - Balanço de Pagamentos - trimestral - saldo - US$ (milhões) | C1: tbysa | D1: original | E1: seasonally adjusted
A2: 1° Trim.1995 | B2: -2569.8
A3: 2° Trim.1995 | B3: -2218.9
A4: 3° Trim.1995 | B4: 282.4
A5: 4° Trim.1995 | B5: -64.7
A6: 1° Trim.1996 | B6: -699.3 | C6: =B6/'PIB em dol'!J4 -> -0.0035686537 | D6: 0.0208024 | E6: 0.0038486536
A7: 2° Trim.1996 | B7: -149 | C7: =B7/'PIB em dol'!J5 -> -0.00074591468 | D7: 0.0101996 | E7: -0.0072933027
A8: 3° Trim.1996 | B8: -1521.6 | C8: =B8/'PIB em dol'!J6 -> -0.0073711466 | D8: -0.0024032 | E8: -0.0097134117
A9: 4° Trim.1996 | B9: -4266.3 | C9: =B9/'PIB em dol'!J7 -> -0.02005269 | D9: -0.008006 | E9: -0.017304247
A10: 1° Trim.1997 | B10: -1066.2 | C10: =B10/'PIB em dol'!J8 -> -0.0049600791 | D10: -0.0016089 | E10: 0.0022336593
A11: 2° Trim.1997 | B11: -1602.2 | C11: =B11/'PIB em dol'!J9 -> -0.0073623325 | D11: -0.0022117 | E11: -0.01391199
A12: 3° Trim.1997 | B12: -1937.5 | C12: =B12/'PIB em dol'!J10 -> -0.0088555033 | D12: -0.0068145 | E12: -0.011390055
A13: 4° Trim.1997 | B13: -3144.8 | C13: =B13/'PIB em dol'!J11 -> -0.014241448 | D13: -0.0014173 | E13: -0.011685763
A14: 1° Trim.1998 | B14: -2101.6 | C14: =B14/'PIB em dol'!J12 -> -0.0095533135 | D14: -0.0020202 | E14: -0.0029077692
A15: 2° Trim.1998 | B15: -245.7 | C15: =B15/'PIB em dol'!J13 -> -0.0011197091 | D15: 0.000377 | E15: -0.0077125933
A16: 3° Trim.1998 | B16: -2080.8 | C16: =B16/'PIB em dol'!J14 -> -0.0095356918 | D16: -0.0072258 | E16: -0.012213057
A17: 4° Trim.1998 | B17: -3199.5 | C17: =B17/'PIB em dol'!J15 -> -0.014814695 | D17: -0.0048286 | E17: -0.012502646
... A29: 4° Trim.2001 | B29: 1077.4 | C29: =B29/'PIB em dol'!J27 -> 0.0077017519 | D29: 0.0109375 | E29: 0.0097659607
A30: 1° Trim.2002 | B30: 791.4 | C30: =B30/'PIB em dol'!J28 -> 0.0058238924 | E30: 0.013969593
A31: 2° Trim.2002 | B31: 1235 | C31: =B31/'PIB em dol'!J29 -> 0.0093316358 | E31: 0.0032363348
A32: 3° Trim.2002 | B32: 5017.3 | C32: =B32/'PIB em dol'!J30 -> 0.038772147 | E32: 0.035358237
A33: 4° Trim.2002 | B33: 4960.1 | C33: =B33/'PIB em dol'!J31 -> 0.039048065 | E33: 0.039843278
A34: 1° Trim.2003 | B34: 3519.4 | C34: =B34/'PIB em dol'!J32 -> 0.028088294 | E34: 0.038559469
A35: 2° Trim.2003 | B35: 6313 | C35: =B35/'PIB em dol'!J33 -> 0.04907036 | E35: 0.038750536
A36: 3° Trim.2003 | B36: 7108.4 | C36: =B36/'PIB em dol'!J34 -> 0.053417799 | E36: 0.04486792
A37: 4° Trim.2003 | B37: 6635.5 | C37: =B37/'PIB em dol'!J35 -> 0.047441752 | E37: 0.043941463
A38: 1° Trim.2004 | B38: 5867.4 | C38: =B38/'PIB em dol'!J36 -> 0.039122977 | E38: 0.045651018
A39: 2° Trim.2004 | B39: 8505.2 | C39: =B39/'PIB em dol'!J37 -> 0.054978757 | E39: 0.047191687
A40: 3° Trim.2004 | B40: 9683.7 | C40: =B40/'PIB em dol'!J38 -> 0.060551035 | E40: 0.054159511
A41: 4° Trim.2004 | B41: 8227.6 | C41: =B41/'PIB em dol'!J39 -> 0.049168508 | E41: 0.045815645
... A127: 2° Trim.2026 | B127: 25454.4 | C127: =B127/'PIB em dol'!J125 -> 0.040774322 | E127: 0.030924751
A128: Fonte | B128: BCB-DSTAT

Sheet balança comercial
A1: Data | B1: 23084 - Balança comercial e Serviços - trimestral - saldo - US$ (milhões) | C1: tbysa | D1: original | E1: seasonally adjusted
A2: 1° Trim.1995 | B2: -4015.5
A3: 2° Trim.1995 | B3: -4036.6
A4: 3° Trim.1995 | B4: -1671.4
A5: 4° Trim.1995 | B5: -1864.2
A6: 1° Trim.1996 | B6: -2201.6 | C6: =B6/'PIB em dol'!G4 -> -0.011050212 | D6: 0.0208024 | E6: -0.0052669078
A7: 2° Trim.1996 | B7: -2120.5 | C7: =B7/'PIB em dol'!G5 -> -0.010207225 | D7: 0.0101996 | E7: -0.016126655
A8: 3° Trim.1996 | B8: -3968.3 | C8: =B8/'PIB em dol'!G6 -> -0.01767861 | D8: -0.0024032 | E8: -0.020220631
A9: 4° Trim.1996 | B9: -6624.9 | C9: =B9/'PIB em dol'!G7 -> -0.030172429 | D9: -0.008006 | E9: -0.027489745
A10: 1° Trim.1997 | B10: -3303.8 | C10: =B10/'PIB em dol'!G8 -> -0.015880371 | D10: -0.0016089 | E10: -0.010097067
A11: 2° Trim.1997 | B11: -4495.5 | C11: =B11/'PIB em dol'!G9 -> -0.02058332 | D11: -0.0022117 | E11: -0.02650275
A12: 3° Trim.1997 | B12: -5158.7 | C12: =B12/'PIB em dol'!G10 -> -0.022512721 | D12: -0.0068145 | E12: -0.025054742
A13: 4° Trim.1997 | B13: -6422.6 | C13: =B13/'PIB em dol'!G11 -> -0.028208022 | D13: -0.0014173 | E13: -0.025525338
A14: 1° Trim.1998 | B14: -4516.8 | C14: =B14/'PIB em dol'!G12 -> -0.022064599 | D14: -0.0020202 | E14: -0.016281295
A15: 2° Trim.1998 | B15: -2737.2 | C15: =B15/'PIB em dol'!G13 -> -0.012661261 | D15: 0.000377 | E15: -0.018580691
A16: 3° Trim.1998 | B16: -5213.8 | C16: =B16/'PIB em dol'!G14 -> -0.023248389 | D16: -0.0072258 | E16: -0.02579041
A17: 4° Trim.1998 | B17: -6143 | C17: =B17/'PIB em dol'!G15 -> -0.028087165 | D17: -0.0048286 | E17: -0.02540448
... A29: 4° Trim.2001 | B29: -893.8 | C29: =B29/'PIB em dol'!G27 -> -0.0063378834 | D29: 0.0109375 | E29: -0.0036551988
A30: 1° Trim.2002 | B30: -580.8 | C30: =B30/'PIB em dol'!G28 -> -0.0048517655 | E30: 0.00093153846
A31: 2° Trim.2002 | B31: -552.2 | C31: =B31/'PIB em dol'!G29 -> -0.0043873797 | E31: -0.01030681
A32: 3° Trim.2002 | B32: 3465.6 | C32: =B32/'PIB em dol'!G30 -> 0.026450116 | E32: 0.023908095
A33: 4° Trim.2002 | B33: 3588.6 | C33: =B33/'PIB em dol'!G31 -> 0.027288074 | E33: 0.029970758
A34: 1° Trim.2003 | B34: 2511.5 | C34: =B34/'PIB em dol'!G32 -> 0.022265466 | E34: 0.02804877
A35: 2° Trim.2003 | B35: 4518.8 | C35: =B35/'PIB em dol'!G33 -> 0.032444464 | E35: 0.026525033
A36: 3° Trim.2003 | B36: 5367.9 | C36: =B36/'PIB em dol'!G34 -> 0.036098128 | E36: 0.033556108
A37: 4° Trim.2003 | B37: 5063.4 | C37: =B37/'PIB em dol'!G35 -> 0.031908297 | E37: 0.034590981
A38: 1° Trim.2004 | B38: 4856 | C38: =B38/'PIB em dol'!G36 -> 0.031691749 | E38: 0.037475053
A39: 2° Trim.2004 | B39: 6897.1 | C39: =B39/'PIB em dol'!G37 -> 0.043601755 | E39: 0.037682325
A40: 3° Trim.2004 | B40: 7834.3 | C40: =B40/'PIB em dol'!G38 -> 0.046190355 | E40: 0.043648335
A41: 4° Trim.2004 | B41: 6242.1 | C41: =B41/'PIB em dol'!G39 -> 0.03314624 | E41: 0.035828925
... A127: 2° Trim.2026 | B127: 10116.5 | C127: =B127/'PIB em dol'!G125 -> 0.014904187 | E127: 0.0089847566
A128: Fonte | B128: BCB-DSTAT

Sheet PIB em dol
B1: Data | C1: 4385 - PIB mensal - Em US$ milhões - US$ (milhões)
B2: 32874 | C2: 37961
B3: 32905 | C3: 36937
B4: 32933 | C4: 37177 | F4: 35125 | G4: =VLOOKUP(F4,B3:D440,3,FALSE) -> 199236 | I4: 35125 | J4: =VLOOKUP(I4,B3:E440,4,FALSE) -> 195956.25
B5: 32964 | C5: 33833 | D5: =SUM(C3:C5) -> 107947 | F5: =EDATE(F4,3) -> 35217 | G5: =VLOOKUP(F5,B4:D441,3,FALSE) -> 207745 | I5: 35217 | J5: =VLOOKUP(I5,B4:E441,4,FALSE) -> 199754.75
B6: 32994 | C6: 38343 | D6: =SUM(C4:C6) -> 109353 | F6: =EDATE(F5,3) -> 35309 | G6: =VLOOKUP(F6,B5:D442,3,FALSE) -> 224469 | I6: 35309 | J6: =VLOOKUP(I6,B5:E442,4,FALSE) -> 206426.5
B7: 33025 | C7: 39533 | D7: =SUM(C5:C7) -> 111709 | F7: =EDATE(F6,3) -> 35400 | G7: =VLOOKUP(F7,B6:D443,3,FALSE) -> 219568 | I7: 35400 | J7: =VLOOKUP(I7,B6:E443,4,FALSE) -> 212754.5
B8: 33055 | C8: 40227 | D8: =SUM(C6:C8) -> 118103 | F8: =EDATE(F7,3) -> 35490 | G8: =VLOOKUP(F8,B7:D444,3,FALSE) -> 208043 | I8: 35490 | J8: =VLOOKUP(I8,B7:E444,4,FALSE) -> 214956.25
B9: 33086 | C9: 42868 | D9: =SUM(C7:C9) -> 122628 | F9: =EDATE(F8,3) -> 35582 | G9: =VLOOKUP(F9,B8:D445,3,FALSE) -> 218405 | I9: 35582 | J9: =VLOOKUP(I9,B8:E445,4,FALSE) -> 217621.25
B10: 33117 | C10: 42315 | D10: =SUM(C8:C10) -> 125410 | F10: =EDATE(F9,3) -> 35674 | G10: =VLOOKUP(F10,B9:D446,3,FALSE) -> 229146 | I10: 35674 | J10: =VLOOKUP(I10,B9:E446,4,FALSE) -> 218790.5
B11: 33147 | C11: 42440 | D11: =SUM(C9:C11) -> 127623 | F11: =EDATE(F10,3) -> 35765 | G11: =VLOOKUP(F11,B10:D447,3,FALSE) -> 227687 | I11: 35765 | J11: =VLOOKUP(I11,B10:E447,4,FALSE) -> 220820.25
B12: 33178 | C12: 41336 | D12: =SUM(C10:C12) -> 126091 | F12: =EDATE(F11,3) -> 35855 | G12: =VLOOKUP(F12,B11:D448,3,FALSE) -> 204708 | I12: 35855 | J12: =VLOOKUP(I12,B11:E448,4,FALSE) -> 219986.5
B13: 33208 | C13: 36348 | D13: =SUM(C11:C13) -> 120124 | E13: =SUM(C2:C13)/4 -> 117329.5 | F13: =EDATE(F12,3) -> 35947 | G13: =VLOOKUP(F13,B12:D449,3,FALSE) -> 216187 | I13: 35947 | J13: =VLOOKUP(I13,B12:E449,4,FALSE) -> 219432
B14: 33239 | C14: 30451 | D14: =SUM(C12:C14) -> 108135 | E14: =SUM(C3:C14)/4 -> 115452 | F14: =EDATE(F13,3) -> 36039 | G14: =VLOOKUP(F14,B13:D450,3,FALSE) -> 224265 | I14: 36039 | J14: =VLOOKUP(I14,B13:E450,4,FALSE) -> 218211.75
B15: 33270 | C15: 29244 | D15: =SUM(C13:C15) -> 96043 | E15: =SUM(C4:C15)/4 -> 113528.75 | F15: =EDATE(F14,3) -> 36130 | G15: =VLOOKUP(F15,B14:D451,3,FALSE) -> 218712 | I15: 36130 | J15: =VLOOKUP(I15,B14:E451,4,FALSE) -> 215968
B16: 33298 | C16: 29646 | D16: =SUM(C14:C16) -> 89341 | E16: =SUM(C5:C16)/4 -> 111646 | F16: =EDATE(F15,3) -> 36220 | G16: =VLOOKUP(F16,B15:D452,3,FALSE) -> 141714 | I16: 36220 | J16: =VLOOKUP(I16,B15:E452,4,FALSE) -> 200219.5
B17: 33329 | C17: 32828 | D17: =SUM(C15:C17) -> 91718 | E17: =SUM(C6:C17)/4 -> 111394.75 | F17: =EDATE(F16,3) -> 36312 | G17: =VLOOKUP(F17,B16:D453,3,FALSE) -> 148541 | I17: 36312 | J17: =VLOOKUP(I17,B16:E453,4,FALSE) -> 183308
B18: 33359 | C18: 34587 | D18: =SUM(C16:C18) -> 97061 | E18: =SUM(C7:C18)/4 -> 110455.75 | F18: =EDATE(F17,3) -> 36404 | G18: =VLOOKUP(F18,B17:D454,3,FALSE) -> 154115 | I18: 36404 | J18: =VLOOKUP(I18,B17:E454,4,FALSE) -> 165770.5
B19: 33390 | C19: 35085 | D19: =SUM(C17:C19) -> 102500 | E19: =SUM(C8:C19)/4 -> 109343.75 | F19: =EDATE(F18,3) -> 36495 | G19: =VLOOKUP(F19,B18:D455,3,FALSE) -> 154920 | I19: 36495 | J19: =VLOOKUP(I19,B18:E455,4,FALSE) -> 149822.5
B20: 33420 | C20: 36544 | D20: =SUM(C18:C20) -> 106216 | E20: =SUM(C9:C20)/4 -> 108423 | F20: =EDATE(F19,3) -> 36586 | G20: =VLOOKUP(F20,B19:D456,3,FALSE) -> 154920 | I20: 36586 | J20: =VLOOKUP(I20,B19:E456,4,FALSE) -> 153124
B21: 33451 | C21: 37802 | D21: =SUM(C19:C21) -> 109431 | E21: =SUM(C10:C21)/4 -> 107156.5 | F21: =EDATE(F20,3) -> 36678 | G21: =VLOOKUP(F21,B20:D457,3,FALSE) -> 161772 | I21: 36678 | J21: =VLOOKUP(I21,B20:E457,4,FALSE) -> 156431.75
B22: 33482 | C22: 35901 | D22: =SUM(C20:C22) -> 110247 | E22: =SUM(C11:C22)/4 -> 105553 | F22: =EDATE(F21,3) -> 36770 | G22: =VLOOKUP(F22,B21:D458,3,FALSE) -> 169058 | I22: 36770 | J22: =VLOOKUP(I22,B21:E458,4,FALSE) -> 160167.5
B23: 33512 | C23: 36887 | D23: =SUM(C21:C23) -> 110590 | E23: =SUM(C12:C23)/4 -> 104164.75 | F23: =EDATE(F22,3) -> 36861 | G23: =VLOOKUP(F23,B22:D459,3,FALSE) -> 169958 | I23: 36861 | J23: =VLOOKUP(I23,B22:E459,4,FALSE) -> 163927
B24: 33543 | C24: 35081 | D24: =SUM(C22:C24) -> 107869 | E24: =SUM(C13:C24)/4 -> 102601 | F24: =EDATE(F23,3) -> 36951 | G24: =VLOOKUP(F24,B23:D460,3,FALSE) -> 135716 | I24: 36951 | J24: =VLOOKUP(I24,B23:E460,4,FALSE) -> 159126
... B125: 36617 | C125: 52099 | D125: =SUM(C123:C125) -> 157652 | E125: =SUM(C114:C125)/4 -> 153857.5 | F125: =EDATE(F124,3) -> 46174 | G125: =VLOOKUP(F125,B124:D561,3,FALSE) -> 678769 | I125: 46174 | J125: =VLOOKUP(I125,B124:E561,4,FALSE) -> 624275.25
B126: 36647 | C126: 54569 | D126: =SUM(C124:C126) -> 160952 | E126: =SUM(C115:C126)/4 -> 155109
B127: 36678 | C127: 55104 | D127: =SUM(C125:C127) -> 161772 | E127: =SUM(C116:C127)/4 -> 156431.75
B128: 36708 | C128: 55853 | D128: =SUM(C126:C128) -> 165526 | E128: =SUM(C117:C128)/4 -> 157795
B129: 36739 | C129: 57258 | D129: =SUM(C127:C129) -> 168215 | E129: =SUM(C118:C129)/4 -> 159146.5
B130: 36770 | C130: 55947 | D130: =SUM(C128:C130) -> 169058 | E130: =SUM(C119:C130)/4 -> 160167.5
B131: 36800 | C131: 58193 | D131: =SUM(C129:C131) -> 171398 | E131: =SUM(C120:C131)/4 -> 161546.25
B132: 36831 | C132: 57145 | D132: =SUM(C130:C132) -> 171285 | E132: =SUM(C121:C132)/4 -> 162785.5
B133: 36861 | C133: 54620 | D133: =SUM(C131:C133) -> 169958 | E133: =SUM(C122:C133)/4 -> 163927
B134: 36892 | C134: 44006 | D134: =SUM(C132:C134) -> 155771 | E134: =SUM(C123:C134)/4 -> 162586.75
B135: 36923 | C135: 44227 | D135: =SUM(C133:C135) -> 142853 | E135: =SUM(C124:C135)/4 -> 160826.25
B136: 36951 | C136: 47483 | D136: =SUM(C134:C136) -> 135716 | E136: =SUM(C125:C136)/4 -> 159126
B137: 36982 | C137: 46705 | D137: =SUM(C135:C137) -> 138415 | E137: =SUM(C126:C137)/4 -> 157777.5
... B439: 46174 | C439: 221267 | D439: =SUM(C437:C439) -> 678769 | E439: =SUM(C428:C439)/4 -> 624275.25
B440: Fonte | C440: BCB-Depec | D440: =SUM(C438:C440) -> 449408 | E440: =SUM(C429:C440)/4 -> 574866

Sheet logRus
A1: Date | B1: GDP deflator | C1: GS3M | D1: GrossTbill_annual | E1: YoY_GrossInflation | F1: Rus | G1: logRus
A2: 33970 | B2: 70.990912 | C2: 3.01 | D2: =1+C2/100 -> 1.0301 | F2: =IF(E2="","",D2/E2) | G2: =IF(F2="","",LN(F2))
A3: 34060 | B3: 71.413619 | C3: 3.14 | D3: =1+C3/100 -> 1.0314 | F3: =IF(E3="","",D3/E3) | G3: =IF(F3="","",LN(F3))
A4: 34151 | B4: 71.838146 | C4: 3.01 | D4: =1+C4/100 -> 1.0301 | F4: =IF(E4="","",D4/E4) | G4: =IF(F4="","",LN(F4))
A5: 34243 | B5: 72.229823 | C5: 3.13 | D5: =1+C5/100 -> 1.0313 | F5: =IF(E5="","",D5/E5) | G5: =IF(F5="","",LN(F5)) | S5: Rus_hat (irs_update) | V5: logrus_statadata
A6: 34335 | B6: 72.575127 | C6: 3.59 | D6: =1+C6/100 -> 1.0359 | E6: =B6/B2 -> 1.0223157 | F6: =IF(E6="","",D6/E6) -> 1.0132877 | G6: =IF(F6="","",LN(F6)) -> 0.013200219 | S6: 0.011527265 | V6: 0.007174
A7: 34425 | B7: 72.925812 | C7: 4.25 | D7: =1+C7/100 -> 1.0425 | E7: =B7/B3 -> 1.0211751 | F7: =IF(E7="","",D7/E7) -> 1.0208827 | G7: =IF(F7="","",LN(F7)) -> 0.020667612 | S7: 0.018620929 | V7: 0.0192438
A8: 34516 | B8: 73.343797 | C8: 4.75 | D8: =1+C8/100 -> 1.0475 | E8: =B8/B4 -> 1.0209589 | F8: =IF(E8="","",D8/E8) -> 1.0259962 | G8: =IF(F8="","",LN(F8)) -> 0.025664052 | S8: 0.024437904 | V8: 0.0254314
A9: 34608 | B9: 73.741722 | C9: 5.76 | D9: =1+C9/100 -> 1.0576 | E9: =B9/B5 -> 1.0209318 | F9: =IF(E9="","",D9/E9) -> 1.0359164 | G9: =IF(F9="","",LN(F9)) -> 0.03528647 | S9: 0.034665802 | V9: 0.0320287
A10: 34700 | B10: 74.141404 | C10: 5.91 | D10: =1+C10/100 -> 1.0591 | E10: =B10/B6 -> 1.0215815 | F10: =IF(E10="","",D10/E10) -> 1.0367259 | G10: =IF(F10="","",LN(F10)) -> 0.036067622 | S10: 0.035630583 | V10: 0.040839
A11: 34790 | B11: 74.497799 | C11: 5.64 | D11: =1+C11/100 -> 1.0564 | E11: =B11/B7 -> 1.021556 | F11: =IF(E11="","",D11/E11) -> 1.0341088 | G11: =IF(F11="","",LN(F11)) -> 0.03353997 | S11: 0.032178963 | V11: 0.0393857
A12: 34881 | B12: 74.864512 | C12: 5.43 | D12: =1+C12/100 -> 1.0543 | E12: =B12/B8 -> 1.0207341 | F12: =IF(E12="","",D12/E12) -> 1.0328841 | G12: =IF(F12="","",LN(F12)) -> 0.032355006 | S12: 0.030921782 | V12: 0.0355326
A13: 34973 | B13: 75.225376 | C13: 5.29 | D13: =1+C13/100 -> 1.0529 | E13: =B13/B9 -> 1.0201196 | F13: =IF(E13="","",D13/E13) -> 1.0321339 | G13: =IF(F13="","",LN(F13)) -> 0.031628384 | S13: 0.030224803 | V13: 0.038806
A14: 35065 | B14: 75.587166 | C14: 5.1 | D14: =1+C14/100 -> 1.051 | E14: =B14/B10 -> 1.0195001 | F14: =IF(E14="","",D14/E14) -> 1.0308974 | G14: =IF(F14="","",LN(F14)) -> 0.030429714 | S14: 0.029048604 | V14: 0.0301179
A15: 35156 | B15: 75.900206 | C15: 5.23 | D15: =1+C15/100 -> 1.0523 | E15: =B15/B11 -> 1.0188248 | F15: =IF(E15="","",D15/E15) -> 1.0328567 | G15: =IF(F15="","",LN(F15)) -> 0.032328428 | S15: 0.030654124 | V15: 0.0332429
A16: 35247 | B16: 76.148471 | C16: 5.24 | D16: =1+C16/100 -> 1.0524 | E16: =B16/B12 -> 1.0171504 | F16: =IF(E16="","",D16/E16) -> 1.0346552 | G16: =IF(F16="","",LN(F16)) -> 0.034068247 | S16: 0.031265467 | V16: 0.0381779
A17: 35339 | B17: 76.555628 | C17: 5.04 | D17: =1+C17/100 -> 1.0504 | E17: =B17/B13 -> 1.0176835 | F17: =IF(E17="","",D17/E17) -> 1.032148 | G17: =IF(F17="","",LN(F17)) -> 0.031642035 | S17: 0.031492384 | V17: 0.0335721
... A37: 37165 | B37: 83.446421 | C37: 1.72 | D37: =1+C37/100 -> 1.0172 | E37: =B37/B33 -> 1.0198275 | F37: =IF(E37="","",D37/E37) -> 0.99742363 | G37: =IF(F37="","",LN(F37)) -> -0.0025796958 | S37: -0.0052457415 | V37: -0.0006314
A38: 37257 | B38: 83.709383 | C38: 1.83 | D38: =1+C38/100 -> 1.0183 | E38: =B38/B34 -> 1.016329 | F38: =IF(E38="","",D38/E38) -> 1.0019393 | G38: =IF(F38="","",LN(F38)) -> 0.0019374655 | S38: -0.0019048184
A39: 37347 | B39: 84.001713 | C39: 1.73 | D39: =1+C39/100 -> 1.0173 | E39: =B39/B35 -> 1.0137794 | F39: =IF(E39="","",D39/E39) -> 1.0034728 | G39: =IF(F39="","",LN(F39)) -> 0.0034667722 | S39: 0.00047603664
A40: 37438 | B40: 84.40376 | C40: 1.66 | D40: =1+C40/100 -> 1.0166 | E40: =B40/B36 -> 1.0146443 | F40: =IF(E40="","",D40/E40) -> 1.0019275 | G40: =IF(F40="","",LN(F40)) -> 0.0019256585 | S40: 0.002905246
A41: 37530 | B41: 84.893534 | C41: 1.21 | D41: =1+C41/100 -> 1.0121 | E41: =B41/B37 -> 1.0173418 | F41: =IF(E41="","",D41/E41) -> 0.99484752 | G41: =IF(F41="","",LN(F41)) -> -0.0051657955 | S41: -0.0026005035
A42: 37622 | B42: 85.309171 | C42: 1.15 | D42: =1+C42/100 -> 1.0115 | E42: =B42/B38 -> 1.0191112 | F42: =IF(E42="","",D42/E42) -> 0.99253151 | G42: =IF(F42="","",LN(F42)) -> -0.0074965143 | S42: -0.0056272023
A43: 37712 | B43: 85.609422 | C43: 0.94 | D43: =1+C43/100 -> 1.0094 | E43: =B43/B39 -> 1.019139 | F43: =IF(E43="","",D43/E43) -> 0.9904439 | G43: =IF(F43="","",LN(F43)) -> -0.0096020533 | S43: -0.010667663
A44: 37803 | B44: 86.098841 | C44: 0.96 | D44: =1+C44/100 -> 1.0096 | E44: =B44/B40 -> 1.020083 | F44: =IF(E44="","",D44/E44) -> 0.98972338 | G44: =IF(F44="","",LN(F44)) -> -0.010329787 | S44: -0.0096994703
A45: 37895 | B45: 86.623546 | C45: 0.91 | D45: =1+C45/100 -> 1.0091 | E45: =B45/B41 -> 1.0203786 | F45: =IF(E45="","",D45/E45) -> 0.98894665 | G45: =IF(F45="","",LN(F45)) -> -0.011114891 | S45: -0.011203906
A46: 37987 | B46: 87.24186 | C46: 0.95 | D46: =1+C46/100 -> 1.0095 | E46: =B46/B42 -> 1.0226551 | F46: =IF(E46="","",D46/E46) -> 0.98713632 | G46: =IF(F46="","",LN(F46)) -> -0.012947136 | S46: -0.010296342
A47: 38078 | B47: 87.945895 | C47: 1.29 | D47: =1+C47/100 -> 1.0129 | E47: =B47/B43 -> 1.0272922 | F47: =IF(E47="","",D47/E47) -> 0.98599012 | G47: =IF(F47="","",LN(F47)) -> -0.014108947 | S47: -0.0094660989
A48: 38169 | B48: 88.503951 | C48: 1.68 | D48: =1+C48/100 -> 1.0168 | E48: =B48/B44 -> 1.0279343 | F48: =IF(E48="","",D48/E48) -> 0.98916828 | G48: =IF(F48="","",LN(F48)) -> -0.010890811 | S48: -0.010942675
A49: 38261 | B49: 89.190057 | C49: 2.22 | D49: =1+C49/100 -> 1.0222 | E49: =B49/B45 -> 1.0296283 | F49: =IF(E49="","",D49/E49) -> 0.99278542 | G49: =IF(F49="","",LN(F49)) -> -0.0072407313 | S49: -0.0064949984
... A85: 41548 | B85: 106.46829 | C85: 0.07 | D85: =1+C85/100 -> 1.0007 | E85: =B85/B81 -> 1.0164052 | F85: =IF(E85="","",D85/E85) -> 0.98454833 | G85: =IF(F85="","",LN(F85)) -> -0.015572292 | S85: -0.013226466
A86: 41640 | B86: 106.87252 | C86: 0.05 | D86: =1+C86/100 -> 1.0005 | E86: =B86/B82 -> 1.0162334 | F86: =IF(E86="","",D86/E86) -> 0.98451796 | G86: =IF(F86="","",LN(F86)) -> -0.015603138
A87: 41730 | B87: 107.47746 | C87: 0.04 | D87: =1+C87/100 -> 1.0004 | E87: =B87/B83 -> 1.0197899 | F87: =IF(E87="","",D87/E87) -> 0.98098642 | G87: =IF(F87="","",LN(F87)) -> -0.019196661
A88: 41821 | B88: 107.91874 | C88: 0.02 | D88: =1+C88/100 -> 1.0002 | E88: =B88/B84 -> 1.0189805 | F88: =IF(E88="","",D88/E88) -> 0.98156929 | G88: =IF(F88="","",LN(F88)) -> -0.018602677
A89: 41913 | B89: 108.02614 | C89: 0.03 | D89: =1+C89/100 -> 1.0003 | E89: =B89/B85 -> 1.014632 | F89: =IF(E89="","",D89/E89) -> 0.98587464 | G89: =IF(F89="","",LN(F89)) -> -0.014226074
A90: 42005 | B90: 107.9673 | C90: 0.03 | D90: =1+C90/100 -> 1.0003 | E90: =B90/B86 -> 1.0102437 | F90: =IF(E90="","",D90/E90) -> 0.99015712 | G90: =IF(F90="","",LN(F90)) -> -0.0098916425
A91: 42095 | B91: 108.58727 | C91: 0.02 | D91: =1+C91/100 -> 1.0002 | E91: =B91/B87 -> 1.010326 | F91: =IF(E91="","",D91/E91) -> 0.98997744 | G91: =IF(F91="","",LN(F91)) -> -0.010073119
A92: 42186 | B92: 108.87528 | C92: 0.02 | D92: =1+C92/100 -> 1.0002 | E92: =B92/B88 -> 1.0088636 | F92: =IF(E92="","",D92/E92) -> 0.99141252 | G92: =IF(F92="","",LN(F92)) -> -0.0086245614
A93: 42278 | B93: 108.87271 | C93: 0.23 | D93: =1+C93/100 -> 1.0023 | E93: =B93/B89 -> 1.0078367 | F93: =IF(E93="","",D93/E93) -> 0.99450637 | G93: =IF(F93="","",LN(F93)) -> -0.0055087766
A94: 42370 | B94: 108.77853 | C94: 0.3 | D94: =1+C94/100 -> 1.003 | E94: =B94/B90 -> 1.0075137 | F94: =IF(E94="","",D94/E94) -> 0.99551993 | G94: =IF(F94="","",LN(F94)) -> -0.0044901357
A95: 42461 | B95: 109.51762 | C95: 0.27 | D95: =1+C95/100 -> 1.0027 | E95: =B95/B91 -> 1.0085677 | F95: =IF(E95="","",D95/E95) -> 0.99418211 | G95: =IF(F95="","",LN(F95)) -> -0.0058348764
A96: 42552 | B96: 109.79773 | C96: 0.29 | D96: =1+C96/100 -> 1.0029 | E96: =B96/B92 -> 1.0084725 | F96: =IF(E96="","",D96/E96) -> 0.99447428 | G96: =IF(F96="","",LN(F96)) -> -0.0055410394
A97: 42644 | B97: 110.32957 | C97: 0.51 | D97: =1+C97/100 -> 1.0051 | E97: =B97/B93 -> 1.0133813 | F97: =IF(E97="","",D97/E97) -> 0.99182808 | G97: =IF(F97="","",LN(F97)) -> -0.0082054978
... A131: 45748 | B131: 142.87791 | C131: 4.42 | D131: =1+C131/100 -> 1.0442 | E131: =B131/B127 -> 1.0249361 | F131: =IF(E131="","",D131/E131) -> 1.0187952 | G131: =IF(F131="","",LN(F131)) -> 0.018620778
A132: 45839 | B132: =B131*B141 -> 144.12695 | C132: 4.07 | D132: =1+C132/100 -> 1.0407 | E132: =B132/B128 -> 1.0290455 | F132: =IF(E132="","",D132/E132) -> 1.0113255 | G132: =IF(F132="","",LN(F132)) -> 0.011261871
A133: 45931 | B133: =B132*B142 -> 144.92083 | C133: 3.68 | D133: =1+C133/100 -> 1.0368 | E133: =B133/B129 -> 1.0287741 | F133: =IF(E133="","",D133/E133) -> 1.0078014 | G133: =IF(F133="","",LN(F133)) -> 0.0077711619
A134: 46023 | B134: =B133*B143 -> 146.81529 | C134: 3.72 | D134: =1+C134/100 -> 1.0372 | E134: =B134/B130 -> 1.0326361 | F134: =IF(E134="","",D134/E134) -> 1.0044197 | G134: =IF(F134="","",LN(F134)) -> 0.0044099428
A135: 46113 | B135: =B134*B144 -> 147.82653 | C135: 3.81 | D135: =1+C135/100 -> 1.0381 | E135: =B135/B131 -> 1.0346353 | F135: =IF(E135="","",D135/E135) -> 1.0033487 | G135: =IF(F135="","",LN(F135)) -> 0.0033431147
B141: 1.008742
B142: 1.0055082
B143: 1.0130724
B144: 1.0068878

Sheet US GDP deflator - FRED
A1: observation_date | B1: NGDPDSAIXUSQ
A2: 32874 | B2: 65.213896
A3: 32964 | B3: 65.944265
A4: 33055 | B4: 66.509499
A5: 33147 | B5: 67.004711
A6: 33239 | B6: 67.661047
A7: 33329 | B7: 68.15751
A8: 33420 | B8: 68.69004
A9: 33512 | B9: 69.097844
A10: 33604 | B10: 69.354633
A11: 33695 | B11: 69.771551
A12: 33786 | B12: 70.112574
A13: 33878 | B13: 70.595286
... A143: 45748 | B143: 142.87791
